{"bookId":"pg-9383","ageRange":"7–10 岁","selection":"按 7–10 岁 阅读者的常用词频与中小学词汇标记筛选","total":417,"words":[{"word":"goat","phonetic":"gәut","translation":"n. 山羊, 替罪羊, 色鬼","definition":"n. any of numerous agile ruminants related to sheep but having a beard and straight horns","pos":"n. 名词","level":"本龄重点","frequency":52},{"word":"paula","phonetic":"'pɔ:lә","translation":"n. 保拉（女子名）","definition":"","pos":"n. 名词","level":"拓展挑战","frequency":33},{"word":"rock","phonetic":"rɒk","translation":"n. 岩石, 岩礁, 石头, 基石, 暗礁, 摇动, 摇滚乐；vt. 摇摆, 摇动, 使摇晃, 使动摇","definition":"n. a lump or mass of hard consolidated mineral matter","pos":"n. 名词","level":"基础巩固","frequency":26},{"word":"sing","phonetic":"siŋ","translation":"vi. 唱, 唱歌, 演唱, 鸣, 啼；vt. 唱, 歌颂","definition":"v. deliver by singing","pos":"vi. 不及物动词","level":"基础巩固","frequency":22},{"word":"cross","phonetic":"krɒs","translation":"n. 十字架, 十字架形物件, 交叉, 十字标, 交叉路, 磨难, 杂交；a. 生气的, 交叉的, 相反的","definition":"n. a wooden structure consisting of an upright post with a transverse piece","pos":"n. 名词","level":"基础巩固","frequency":22},{"word":"longer","phonetic":"'lɔŋɡә. 'lɔ:ŋ-","translation":"adv. 比较久","definition":"n. a person with a strong desire for something","pos":"adv. 副词","level":"基础巩固","frequency":25},{"word":"dear","phonetic":"'diә","translation":"n. 亲爱的人；a. 亲爱的, 昂贵的, 严重的, 急迫的","definition":"s. with or in a close or intimate relationship","pos":"n. 名词","level":"基础巩固","frequency":19},{"word":"bath","phonetic":"bæθ.bɑ:θ","translation":"n. 沐浴, 浴室","definition":"n. a vessel containing liquid in which something is immersed (as to process it or to maintain it at a constant temperature or to lubricate it)","pos":"n. 名词","level":"基础巩固","frequency":18},{"word":"sky","phonetic":"skai","translation":"n. 天空, 天色, 天堂；vt. 击向空中, 挂在高处","definition":"n. the atmosphere and outer space as viewed from the earth","pos":"n. 名词","level":"基础巩固","frequency":17},{"word":"rain","phonetic":"rein","translation":"n. 雨, 下雨, 雨天；vi. 下雨","definition":"n. water falling in drops from vapor condensed in the atmosphere","pos":"n. 名词","level":"基础巩固","frequency":16},{"word":"immediately","phonetic":"i'mi:diәtli","translation":"adv. 直接地, 立刻, 立即","definition":"r. without delay or hesitation; with no time intervening","pos":"adv. 副词","level":"基础巩固","frequency":13},{"word":"flock","phonetic":"flɒk","translation":"n. 兽群, 鸟群, 一群人, 大量, 棉束；vi. 成群而行, 聚集","definition":"n. a church congregation guided by a pastor","pos":"n. 名词","level":"拓展挑战","frequency":16},{"word":"front","phonetic":"frʌnt","translation":"n. 前面, 开头, 前线, 阵线, 态度；vt. 面对, 朝向, 对抗","definition":"n. the side that is forward or prominent","pos":"n. 名词","level":"基础巩固","frequency":11},{"word":"found","phonetic":"faund","translation":"vt. 建立, 创立, 铸造；find的过去式和过去分词","definition":"n. food and lodging provided in addition to money","pos":"vt. 及物动词","level":"基础巩固","frequency":12},{"word":"aunt","phonetic":"ɑ:nt","translation":"n. 阿姨, 姨妈, 舅妈, 姑妈, 伯母","definition":"n. the sister of your father or mother; the wife of your uncle","pos":"n. 名词","level":"基础巩固","frequency":11},{"word":"grandmother","phonetic":"'grændmʌðә","translation":"n. 祖母, 女祖先","definition":"n the mother of your father or mother","pos":"n. 名词","level":"基础巩固","frequency":12},{"word":"landlord","phonetic":"'lændlɒ:d","translation":"n. 房东, 地主","definition":"n. a landowner who leases to others","pos":"n. 名词","level":"基础巩固","frequency":14},{"word":"beautiful","phonetic":"'bju:tiful","translation":"a. 美丽的","definition":"a. delighting the senses or exciting intellectual or emotional admiration","pos":"adj. 形容词","level":"基础巩固","frequency":10},{"word":"mountain","phonetic":"'mauntin","translation":"n. 山, 山脉, 大堆","definition":"n. a land mass that projects well above its surroundings; higher than a hill","pos":"n. 名词","level":"基础巩固","frequency":10},{"word":"blue","phonetic":"blu:","translation":"n. 蓝色；a. 蓝色的, 下流的, 忧郁的","definition":"n. blue color or pigment; resembling the color of the clear sky in the daytime","pos":"n. 名词","level":"基础巩固","frequency":10},{"word":"lost","phonetic":"lɒst","translation":"a. 失去的, 遗失的, 迷惑的；lose的过去式和过去分词","definition":"a. no longer in your possession or control; unable to be found or recovered","pos":"adj. 形容词","level":"基础巩固","frequency":11},{"word":"fast","phonetic":"fɑ:st","translation":"a. 快速的, 紧的；adv. 很快地, 紧紧地, 彻底地","definition":"n. abstaining from food","pos":"adj. 形容词","level":"基础巩固","frequency":9},{"word":"shed","phonetic":"ʃed","translation":"n. 车棚, 小屋, 脱落之物, 分水岭；vt. 使流出, 放射, 脱落, 散发, 摆脱","definition":"n. an outbuilding with a single story; used for shelter or storage","pos":"n. 名词","level":"本龄重点","frequency":12},{"word":"song","phonetic":"sɒŋ","translation":"n. 歌, 曲, 鸣声, 歌唱, 歌曲, 诗歌","definition":"n. a short musical composition with words","pos":"n. 名词","level":"基础巩固","frequency":9},{"word":"singing","phonetic":"'siŋiŋ","translation":"n. 歌唱, 歌声","definition":"n. the act of singing vocal music","pos":"n. 名词","level":"拓展挑战","frequency":11},{"word":"swallow","phonetic":"'swɒlәu","translation":"n. 燕子, 吞咽, 喉；vt. 咽, 淹没, 吞没, 耗尽, 轻信, 忍受, 抑制","definition":"n. a small amount of liquid food","pos":"n. 名词","level":"本龄重点","frequency":11},{"word":"valley","phonetic":"'væli","translation":"n. 山谷, 溪谷, 流域, 凹地","definition":"n. a long depression in the surface of the land that usually contains a river","pos":"n. 名词","level":"基础巩固","frequency":10},{"word":"glad","phonetic":"glæd","translation":"a. 高兴的, 喜欢的, 情愿的","definition":"a. showing or causing joy and pleasure; especially made happy","pos":"adj. 形容词","level":"基础巩固","frequency":9},{"word":"surely","phonetic":"'ʃuәli","translation":"adv. 的确地, 安全地","definition":"r. definitely or positively (`sure' is sometimes used informally for `surely')","pos":"adv. 副词","level":"基础巩固","frequency":9},{"word":"suddenly","phonetic":"'sʌdәnli","translation":"adv. 突然, 意外, 忽然, 迅速, 即席作成, 即刻, 急速","definition":"r. happening unexpectedly","pos":"adv. 副词","level":"基础巩固","frequency":8},{"word":"lay","phonetic":"lei","translation":"vt. 放置, 产, 铺设, 布置, 提出, 平息；vi. 下蛋, 打赌","definition":"v. put in a horizontal position","pos":"vt. 及物动词","level":"基础巩固","frequency":7},{"word":"steep","phonetic":"sti:p","translation":"n. 浸渍, 悬崖；a. 险峻的, 陡峭的, 急剧升降的, 夸大的","definition":"n. a steep place (as on a hill)","pos":"n. 名词","level":"本龄重点","frequency":9},{"word":"standing","phonetic":"'stændiŋ","translation":"n. 起立, 持续, 身分；a. 立着的, 不动的, 经常的, 持续的","definition":"n. social or financial or professional status or reputation","pos":"n. 名词","level":"基础巩固","frequency":11},{"word":"sleep","phonetic":"sli:p","translation":"n. 睡眠, 静止, 昏迷, 麻木, 长眠, 冬眠；vi. 睡觉, 睡眠, 静止","definition":"n. a natural and periodic state of rest during which consciousness of the world is suspended","pos":"n. 名词","level":"基础巩固","frequency":6},{"word":"green","phonetic":"gri:n","translation":"n. 绿色, 绿色颜料；a. 绿色的, 未成熟的, 新鲜的, 青春的, 无经验的, 脸色发青的","definition":"n. green color or pigment; resembling the color of growing grass","pos":"n. 名词","level":"基础巩固","frequency":5},{"word":"saw","phonetic":"sɒ:","translation":"n. 锯子, 谚语；vt. 锯, 锯开, 来回移动","definition":"n. hand tool having a toothed blade for cutting","pos":"n. 名词","level":"拓展挑战","frequency":10},{"word":"sun","phonetic":"sʌn","translation":"n. 太阳, 日, 日光, 阳光；vt. 晒","definition":"n. the star that is the source of light and heat for the planets in the solar system","pos":"n. 名词","level":"基础巩固","frequency":7},{"word":"coming","phonetic":"'kʌmiŋ","translation":"n. 来临；a. 就要来的, 接着的","definition":"n the act of drawing spatially closer to something","pos":"n. 名词","level":"本龄重点","frequency":7},{"word":"pleasure","phonetic":"'pleʒә","translation":"n. 快乐, 愉快, 令人高兴的事, 娱乐, 希望；v. (使)高兴","definition":"n. a fundamental feeling that is hard to define but that people desire to experience","pos":"n. 名词","level":"基础巩固","frequency":6},{"word":"brown","phonetic":"braun","translation":"n. 褐色；a. 褐色的","definition":"n. an orange of low brightness and saturation","pos":"n. 名词","level":"基础巩固","frequency":4},{"word":"visit","phonetic":"'vizit","translation":"n. 拜访, 访问, 游览, 视察；vt. 拜访, 访问, 参观, 视察, 降临","definition":"n. the act of going to see some person or place or thing for a short time","pos":"n. 名词","level":"基础巩固","frequency":4},{"word":"joy","phonetic":"dʒɒi","translation":"n. 欢喜, 乐事, 高兴；vt. 使快乐, 令人高兴","definition":"n. the emotion of great happiness","pos":"n. 名词","level":"基础巩固","frequency":5},{"word":"made","phonetic":"meid","translation":"a. 人工制成的, 成功的, 创造的；make的过去式和过去分词","definition":"s. produced by a manufacturing process; rope and nails\"","pos":"adj. 形容词","level":"本龄重点","frequency":8},{"word":"silent","phonetic":"'sailәnt","translation":"a. 沉默的, 安静的, 无声的, 静止的","definition":"s. marked by absence of sound","pos":"adj. 形容词","level":"基础巩固","frequency":5},{"word":"dark","phonetic":"dɑ:k","translation":"n. 黑暗, 夜, 黄昏, 模糊；a. 黑暗的, 暗的, 深色的, 隐密的, 模糊的, 无知的","definition":"n. absence of light or illumination","pos":"n. 名词","level":"基础巩固","frequency":4},{"word":"forget","phonetic":"fә'get","translation":"vt. 忘记, 忽略, 忘；vi. 忘记","definition":"v. dismiss from the mind; stop remembering","pos":"vt. 及物动词","level":"基础巩固","frequency":4},{"word":"stone","phonetic":"stәun","translation":"n. 石头, 宝石, 果核, 纪念碑, 结石；vt. 投扔石子, 铺石头","definition":"n. building material consisting of a piece of rock hewn in a definite shape for a special purpose","pos":"n. 名词","level":"基础巩固","frequency":4},{"word":"weather","phonetic":"'weðә","translation":"n. 天气, 气象, 处境；a. 迎风的","definition":"n. the atmospheric conditions that comprise the state of the atmosphere in terms of temperature and wind and clouds and precipitation","pos":"n. 名词","level":"基础巩固","frequency":4},{"word":"creature","phonetic":"'kri:tʃә","translation":"n. 人, 动物, 创造物, 生物","definition":"n. a human being; `wight' is an archaic term","pos":"n. 名词","level":"基础巩固","frequency":6},{"word":"surprise","phonetic":"sә'praiz","translation":"n. 惊奇, 奇袭, 诧异；vt. 使惊奇, 撞见, 奇袭","definition":"n. the astonishment you feel when something totally unexpected happens to you","pos":"n. 名词","level":"基础巩固","frequency":3},{"word":"delight","phonetic":"di'lait","translation":"n. 高兴, 愉快；vt. 使高兴, 乐于","definition":"n. a feeling of extreme pleasure or satisfaction","pos":"n. 名词","level":"本龄重点","frequency":5},{"word":"climb","phonetic":"klaim","translation":"v. 攀登, 上升, 爬；n. 攀登, 爬升","definition":"n. an event that involves rising to a higher point (as in altitude or temperature or intensity etc.)","pos":"v. 动词","level":"基础巩固","frequency":4},{"word":"meal","phonetic":"mi:l","translation":"n. 一餐, 膳食, 粗粉；vi. 进餐","definition":"n. the food served and eaten at one time","pos":"n. 名词","level":"基础巩固","frequency":4},{"word":"meanwhile","phonetic":"'mi:nhwail","translation":"n. 其时, 其间；adv. 同时, 于此时","definition":"r. at the same time but in another place","pos":"n. 名词","level":"基础巩固","frequency":4},{"word":"running","phonetic":"'rʌniŋ","translation":"n. 赛跑, 流出, 运转；a. 流动的, 跑着的, 连续的","definition":"n. the state of being in operation","pos":"n. 名词","level":"本龄重点","frequency":4},{"word":"thinking","phonetic":"'θiŋkiŋ","translation":"n. 思考, 思想；a. 思考的, 有理性的","definition":"n. the process of using your mind to consider something carefully","pos":"n. 名词","level":"基础巩固","frequency":4},{"word":"alone","phonetic":"ә'lәun","translation":"a. 孤独的, 单独的, 独自的；adv. 独自地","definition":"s. isolated from others","pos":"adj. 形容词","level":"基础巩固","frequency":3},{"word":"bright","phonetic":"brait","translation":"a. 明亮的, 聪明的, 鲜明的, 欢快的；adv. 明亮地, 欢快地","definition":"a. emitting or reflecting light readily or in large amounts","pos":"adj. 形容词","level":"基础巩固","frequency":3},{"word":"deep","phonetic":"di:p","translation":"a. 深的；adv. 深入地","definition":"n. the central and most intense or profound part","pos":"adj. 形容词","level":"基础巩固","frequency":3},{"word":"fresh","phonetic":"freʃ","translation":"a. 新鲜的, 新奇的, 另外的, 淡的, 精神饱满的, 冒失的；adv. 最新地, 刚刚","definition":"a. recently made, produced, or harvested","pos":"adj. 形容词","level":"基础巩固","frequency":3},{"word":"prevent","phonetic":"pri'vent","translation":"v. 预防, 防止, 阻止, 妨碍","definition":"v. keep from happening or arising; make impossible","pos":"v. 动词","level":"基础巩固","frequency":3},{"word":"promise","phonetic":"'prɒmis","translation":"n. 诺言, 约定的事情, 有指望；vt. 允诺, 约定, 预示","definition":"n. a verbal commitment by one person to another agreeing to do (or not to do) something in the future","pos":"n. 名词","level":"基础巩固","frequency":3},{"word":"quiet","phonetic":"'kwaiәt","translation":"n. 安静, 闲适, 平静；a. 安静的, 静止的, 寂静的, 朴素的, 从容的, 暗中的","definition":"a. characterized by an absence or near absence of agitation or activity","pos":"n. 名词","level":"基础巩固","frequency":3},{"word":"secret","phonetic":"'si:krit","translation":"n. 秘密, 机密, 秘诀, 秘方；a. 秘密的, 极机密的, 隐蔽的, 暗中的, 神秘的, 偏僻的","definition":"n. something that should remain hidden from others (especially information that is not to be passed on)","pos":"n. 名词","level":"基础巩固","frequency":3},{"word":"shoulder","phonetic":"'ʃәuldә","translation":"n. 肩, 肩膀, 衣肩；vt. 肩负, 负担, 担任","definition":"n. the part of the body between the neck and the upper arm","pos":"n. 名词","level":"基础巩固","frequency":3},{"word":"trouble","phonetic":"'trʌbl","translation":"n. 烦恼, 麻烦, 困难, 动乱, 故障；vt. 困扰, 麻烦, 使烦恼, 折磨","definition":"n. a source of difficulty","pos":"n. 名词","level":"基础巩固","frequency":3},{"word":"weight","phonetic":"weit","translation":"n. 重, 重量, 体重, 砝码, 重大, 影响, 力量；vt. 加重量于, 压迫, 使加权, 称重量","definition":"n. the vertical force exerted by a mass as a result of gravity","pos":"n. 名词","level":"基础巩固","frequency":3},{"word":"fear","phonetic":"fiә","translation":"n. 恐怖, 害怕, 担心；v. 害怕, 恐惧, 为...担心, 敬畏","definition":"n. an emotion experienced in anticipation of some specific pain or danger (usually accompanied by a desire to flee or fight)","pos":"n. 名词","level":"基础巩固","frequency":2},{"word":"gone","phonetic":"gɒn","translation":"a. 离去的, 死去的, 用完的；go的过去分词","definition":"s. no longer retained","pos":"adj. 形容词","level":"本龄重点","frequency":5},{"word":"belong","phonetic":"bi'lɒŋ","translation":"vi. 属于, 合适","definition":"v. be owned by; be in the possession of","pos":"vi. 不及物动词","level":"基础巩固","frequency":4},{"word":"afraid","phonetic":"ә'freid","translation":"a. 害怕的, 恐怕的, 遗憾的","definition":"a. filled with fear or apprehension","pos":"adj. 形容词","level":"基础巩固","frequency":3},{"word":"beside","phonetic":"bi'said","translation":"prep. 在旁边","definition":"n. At the side of; on one side of.","pos":"prep. 介词","level":"基础巩固","frequency":3},{"word":"everywhere","phonetic":"'evrihwєә","translation":"adv. 各处, 到处","definition":"r. to or in any or all places; (`everyplace' is used informally for `everywhere')","pos":"adv. 副词","level":"基础巩固","frequency":3},{"word":"heaven","phonetic":"'hevn","translation":"n. 天堂, 上帝, 天空","definition":"n. the abode of God and the angels","pos":"n. 名词","level":"基础巩固","frequency":3},{"word":"milk","phonetic":"milk","translation":"n. 奶, 乳状物；vt. 挤乳, 榨取","definition":"n. a white nutritious liquid secreted by mammals and used as food by human beings","pos":"n. 名词","level":"基础巩固","frequency":3},{"word":"path","phonetic":"pɑ:θ","translation":"n. 路径, 小路, 道路, 途径, 路线, 轨道","definition":"n. a way especially designed for a particular use","pos":"n. 名词","level":"基础巩固","frequency":3},{"word":"till","phonetic":"til","translation":"prep. 直到, 在...以前, 迄；conj. 直到...为止","definition":"n. unstratified soil deposited by a glacier; consists of sand and clay and gravel and boulders mixed together","pos":"prep. 介词","level":"基础巩固","frequency":3},{"word":"bear","phonetic":"bєә","translation":"n. 熊；vt. 忍受, 支承, 产生, 怀有, 通过卖空使跌价","definition":"n. massive plantigrade carnivorous or omnivorous mammals with long shaggy coats and strong claws","pos":"n. 名词","level":"基础巩固","frequency":5},{"word":"distance","phonetic":"'distәns","translation":"n. 距离, 远方, 遥远","definition":"n. the property created by the space between two objects or points","pos":"n. 名词","level":"基础巩固","frequency":3},{"word":"protection","phonetic":"prә'tekʃәn","translation":"n. 保护, 防卫, 贸易保护制度","definition":"n. the activity of protecting someone or something","pos":"n. 名词","level":"基础巩固","frequency":3},{"word":"spot","phonetic":"spɒt","translation":"n. 污点, 地点, 斑点, 点, 娱乐场所, 处境, 少量；a. 当场的, 现场的, 现货买卖的, 现金交易的, 抽样的","definition":"n. a short section or illustration (as between radio or tv programs or in a magazine) that is often used for advertising","pos":"n. 名词","level":"基础巩固","frequency":3},{"word":"dangerous","phonetic":"'deindʒәrәs","translation":"a. 危险的","definition":"a. involving or causing danger or risk; liable to hurt or harm","pos":"adj. 形容词","level":"基础巩固","frequency":2},{"word":"direction","phonetic":"di'rekʃәn","translation":"n. 方向, 指导, 趋势","definition":"n. a line leading to a place or point","pos":"n. 名词","level":"基础巩固","frequency":2},{"word":"egg","phonetic":"eg","translation":"n. 蛋, 卵；vt. 挑唆, 煽动, 调蛋黄","definition":"n. animal reproductive body consisting of an ovum or embryo together with nutritive and protective envelopes; especially the thin-shelled reproductive body laid","pos":"n. 名词","level":"基础巩固","frequency":2},{"word":"feed","phonetic":"fi:d","translation":"n. 饲料, 一餐, 饲养；vt. 喂, 饲养, 放牧, 靠...为生","definition":"n. food for domestic livestock","pos":"n. 名词","level":"基础巩固","frequency":2},{"word":"hardly","phonetic":"'hɑ:dli","translation":"adv. 刚刚, 几乎不, 勉强是","definition":"r. almost not","pos":"adv. 副词","level":"基础巩固","frequency":2},{"word":"heavy","phonetic":"'hevi","translation":"a. 重的, 巨大的, 沉重的, 笨重的, 过度的；adv. 沉重地","definition":"n. an actor who plays villainous roles","pos":"adj. 形容词","level":"基础巩固","frequency":2},{"word":"hole","phonetic":"hәul","translation":"n. 孔, 洞, 穴, 漏洞；vt. 挖洞, 掘坑","definition":"n. an opening into or through something","pos":"n. 名词","level":"基础巩固","frequency":2},{"word":"impossible","phonetic":"im'pɒsәbl","translation":"a. 不可能的, 难以置信的, 令人无法忍受的","definition":"n. something that cannot be done","pos":"adj. 形容词","level":"基础巩固","frequency":2},{"word":"leg","phonetic":"leg","translation":"n. 腿, 假腿, 路程；vi. 走, 跑","definition":"n. a human limb; commonly used to refer to a whole limb but technically only the part of the limb between the knee and ankle","pos":"n. 名词","level":"基础巩固","frequency":2},{"word":"nobody","phonetic":"'nәubɒdi","translation":"n. 小人物, 无名小卒；pron. 无人, 没有人","definition":"n a person of no influence","pos":"n. 名词","level":"基础巩固","frequency":2},{"word":"reply","phonetic":"ri'plai","translation":"n. 答复, 回答, 答辩；vi. 答复, 回答, 回击, 反响, 答辩","definition":"n. the speech act of continuing a conversational exchange","pos":"n. 名词","level":"基础巩固","frequency":2},{"word":"sorry","phonetic":"'sɒri","translation":"a. 难过的, 悲哀的, 遗憾的","definition":"a feeling or expressing regret or sorrow or a sense of loss over something done or undone","pos":"adj. 形容词","level":"基础巩固","frequency":2},{"word":"strange","phonetic":"streindʒ","translation":"a. 奇怪的, 陌生的, 生疏的, 不熟悉的, 不可思议的, 外行的, 外地的, 异乡的","definition":"a. being definitely out of the ordinary and unexpected; slightly odd or even a bit weird","pos":"adj. 形容词","level":"基础巩固","frequency":2},{"word":"trust","phonetic":"trʌst","translation":"n. 信任, 信赖, 相信, 受托, 职责, 信心, 托拉斯；a. 信托的, 托拉斯的","definition":"n. something (as property) held by one party (the trustee) for the benefit of another (the beneficiary)","pos":"n. 名词","level":"基础巩固","frequency":2},{"word":"usual","phonetic":"'ju:ʒuәl","translation":"a. 平常的, 通常的","definition":"a. occurring or encountered or experienced or observed frequently or in accordance with regular practice or procedure","pos":"adj. 形容词","level":"基础巩固","frequency":2},{"word":"besides","phonetic":"bi'saidz","translation":"prep. 除...之外；adv. 而且, 此外","definition":"r. making an additional point; anyway; besides, we can't afford it\"","pos":"prep. 介词","level":"本龄重点","frequency":4},{"word":"peace","phonetic":"pi:s","translation":"n. 和平, 和约, 治安, 和睦, 安宁, 静寂；vi. 安静下来, 不作声","definition":"n. the state prevailing during the absence of war","pos":"n. 名词","level":"基础巩固","frequency":1},{"word":"aside","phonetic":"ә'said","translation":"n. 小声说的话, 旁白；adv. 在一边, 离开, 另外","definition":"n. a line spoken by an actor to the audience but not intended for others on the stage","pos":"n. 名词","level":"基础巩固","frequency":3},{"word":"pleased","phonetic":"pli:zd","translation":"a. 高兴的, 喜欢的, 满足的","definition":"a. experiencing or manifesting pleasure","pos":"adj. 形容词","level":"基础巩固","frequency":3},{"word":"alive","phonetic":"ә'laiv","translation":"a. 活着的, 活泼的, 敏感的, 热闹的","definition":"a. possessing life","pos":"adj. 形容词","level":"基础巩固","frequency":2},{"word":"dare","phonetic":"dєә","translation":"n. 挑战, 挑动, 大胆；v. 敢, 胆敢","definition":"n. a challenge to do something dangerous or foolhardy","pos":"n. 名词","level":"本龄重点","frequency":2},{"word":"discovery","phonetic":"dis'kʌvәri","translation":"n. 发现, 被发现的事物","definition":"n. the act of discovering something","pos":"n. 名词","level":"基础巩固","frequency":2},{"word":"grass","phonetic":"græs","translation":"n. 草, 草原, 牧场","definition":"n. narrow-leaved green herbage: grown as lawns; used as pasture for grazing animals; cut and dried as hay","pos":"n. 名词","level":"基础巩固","frequency":2},{"word":"height","phonetic":"hait","translation":"n. 高度, 海拔, 高地, 顶点","definition":"n. the vertical dimension of extension; distance from the base of something to the top","pos":"n. 名词","level":"基础巩固","frequency":2},{"word":"knife","phonetic":"naif","translation":"n. 小刀, 匕首；vt. 切割, 伤害, 切, 戳","definition":"n. edge tool used as a cutting instrument; has a pointed blade with a sharp edge and a handle","pos":"n. 名词","level":"基础巩固","frequency":2},{"word":"lonely","phonetic":"'lәunli","translation":"a. 孤单的, 孤寂的, 荒凉的","definition":"s. marked by dejection from being alone","pos":"adj. 形容词","level":"本龄重点","frequency":2},{"word":"loud","phonetic":"laud","translation":"a. 大声的, 不断的, 喧吵的；adv. 高声地, 大声地","definition":"a. characterized by or producing sound of great volume or intensity","pos":"adj. 形容词","level":"本龄重点","frequency":2},{"word":"lovely","phonetic":"'lʌvli","translation":"a. 可爱的, 有趣的","definition":"s. appealing to the emotions as well as the eye","pos":"adj. 形容词","level":"基础巩固","frequency":2},{"word":"plenty","phonetic":"'plenti","translation":"n. 充分, 很多, 丰富；a. 很多的, 足够的, 丰富的","definition":"n. a full supply","pos":"n. 名词","level":"基础巩固","frequency":2},{"word":"stick","phonetic":"stik","translation":"n. 棍, 棒, 刺, 枯枝, 茎, 条状物；vt. 插进, 刺入, 钉住, 伸出, 粘贴, 停止","definition":"n. an implement consisting of a length of wood","pos":"n. 名词","level":"基础巩固","frequency":2},{"word":"tired","phonetic":"taiәd","translation":"a. 疲累的, 疲乏的, 厌倦的","definition":"a. depleted of strength or energy","pos":"adj. 形容词","level":"基础巩固","frequency":2},{"word":"winter","phonetic":"'wintә","translation":"n. 冬季, 萧条期, 衰退期；a. 冬天的","definition":"n. the coldest season of the year; in the northern hemisphere it extends from the winter solstice to the vernal equinox","pos":"n. 名词","level":"基础巩固","frequency":2},{"word":"yellow","phonetic":"'jelәu","translation":"n. 黄色；a. 黄色的","definition":"n. yellow color or pigment; the chromatic color resembling the hue of sunflowers or ripe lemons","pos":"n. 名词","level":"基础巩固","frequency":2},{"word":"affair","phonetic":"ә'fєә","translation":"n. 事件, 事务, 恋爱事件","definition":"n. a usually secretive or illicit sexual relationship","pos":"n. 名词","level":"基础巩固","frequency":2},{"word":"aware","phonetic":"ә'wєә","translation":"a. 知道的, 有觉悟的","definition":"a. (sometimes followed by `of') having or showing knowledge or understanding or realization or perception","pos":"adj. 形容词","level":"基础巩固","frequency":2},{"word":"earn","phonetic":"ә:n","translation":"vt. 赚得, 获得, 博得","definition":"v. acquire or deserve by one's efforts or actions","pos":"vt. 及物动词","level":"基础巩固","frequency":2},{"word":"narrow","phonetic":"'nærәu","translation":"n. 狭窄部分, 隘路；a. 狭窄的, 仔细的, 有限的, 勉强的, 狭隘的, 手紧的","definition":"n. a narrow strait connecting two bodies of water","pos":"n. 名词","level":"基础巩固","frequency":2},{"word":"otherwise","phonetic":"'ʌðәwaiz","translation":"adv. 否则, 不同地, 别的方式","definition":"s. other than as supposed or expected","pos":"adv. 副词","level":"基础巩固","frequency":2},{"word":"prepared","phonetic":"pri'pєәd","translation":"a. 准备好的, 特制的","definition":"a. made ready or fit or suitable beforehand","pos":"adj. 形容词","level":"基础巩固","frequency":2},{"word":"struggle","phonetic":"'strʌgl","translation":"n. 斗争, 努力, 奋斗；vi. 努力, 奋斗, 挣扎","definition":"n. an energetic attempt to achieve something","pos":"n. 名词","level":"基础巩固","frequency":2},{"word":"sunny","phonetic":"'sʌni","translation":"a. 阳光充足的, 乐观的, 快乐的, 像太阳的","definition":"s bright and pleasant; promoting a feeling of cheer","pos":"adj. 形容词","level":"本龄重点","frequency":4},{"word":"afternoon","phonetic":"'ɑ:ftә'nu:n","translation":"n. 午后, 下午","definition":"n. the part of the day between noon and evening","pos":"n. 名词","level":"基础巩固","frequency":1},{"word":"anyway","phonetic":"'eniwei","translation":"adv. 无论如何, 至少","definition":"r used to indicate that a statement explains or supports a previous statement; anyhow, they're quiet\"; anyway, it's gone\"; in any case, there was a brief scuffl","pos":"adv. 副词","level":"基础巩固","frequency":1},{"word":"bag","phonetic":"bæg","translation":"n. 袋子, 袋状物；vt. 使膨大, 装袋, 猎获","definition":"n. a flexible container with a single opening","pos":"n. 名词","level":"基础巩固","frequency":1},{"word":"circle","phonetic":"'sә:kl","translation":"n. 圆周, 社交圈, 循环, 范围；vt. 围着, 环绕","definition":"n. ellipse in which the two axes are of equal length; a plane curve generated by one point moving at a constant distance from a fixed point","pos":"n. 名词","level":"基础巩固","frequency":1},{"word":"cool","phonetic":"ku:l","translation":"n. 凉爽, 凉爽的空气；a. 凉爽的, 冷淡的, 冷静的","definition":"n. the quality of being at a refreshingly low temperature","pos":"n. 名词","level":"基础巩固","frequency":1},{"word":"corner","phonetic":"'kɒ:nә","translation":"n. 角落, 转角, 窘境；vt. 迫至一隅, 垄断, 使陷入绝境","definition":"n. a place off to the side of an area","pos":"n. 名词","level":"基础巩固","frequency":1},{"word":"cry","phonetic":"krai","translation":"n. 叫声, 哭声, 大叫；vi. 哭, 叫, 喊","definition":"n. a loud utterance; often in protest or opposition","pos":"n. 名词","level":"基础巩固","frequency":1},{"word":"earth","phonetic":"ә:θ","translation":"n. 地球, 泥土, 世界, 尘世；vt. 埋入土中, 赶入洞内","definition":"n. the 3rd planet from the sun; the planet we live on","pos":"n. 名词","level":"基础巩固","frequency":1},{"word":"edge","phonetic":"edʒ","translation":"n. 边缘, 尖锐, 刀刃, 优势；vt. 使锐利, 挤进, 镶边","definition":"n. the boundary of a surface","pos":"n. 名词","level":"基础巩固","frequency":1},{"word":"excellent","phonetic":"'ekslәnt","translation":"a. 优良的, 杰出的, 出色的","definition":"s. very good; of the highest quality","pos":"adj. 形容词","level":"基础巩固","frequency":1},{"word":"express","phonetic":"ik'spres","translation":"n. 快车, 快递, 专使；a. 明确的, 丝毫不差的, 专门的, 快的","definition":"n. mail that is distributed by a rapid and efficient system","pos":"n. 名词","level":"基础巩固","frequency":1},{"word":"festival","phonetic":"'festәvәl","translation":"a. 节日的, 喜庆的, 快乐的；n. 节日, 庆祝, 欢宴","definition":"n. a day or period of time set aside for feasting and celebration","pos":"adj. 形容词","level":"基础巩固","frequency":1},{"word":"finish","phonetic":"'finiʃ","translation":"n. 完成, 结束, 末道漆, 磨光, 完美；vt. 完成, 结束, 用完, 毁掉","definition":"n. the place designated as the end (as of a race or journey)","pos":"n. 名词","level":"基础巩固","frequency":1},{"word":"gold","phonetic":"gәuld","translation":"n. 黄金, 钱财, 金块, 金色, 宝贵；a. 金的, 似金的, 金色的, 金制的","definition":"n. coins made of gold","pos":"n. 名词","level":"基础巩固","frequency":1},{"word":"guess","phonetic":"ges","translation":"n. 猜测, 臆测；v. 猜测, 臆测","definition":"n. a message expressing an opinion based on incomplete evidence","pos":"n. 名词","level":"基础巩固","frequency":1},{"word":"hang","phonetic":"hæŋ","translation":"n. 悬挂, 诀窍, 意义；vt. 悬挂, 附着, 装饰, 垂下, 踌躇, 绞死, 使悬而未决","definition":"n. the way a garment hangs","pos":"n. 名词","level":"基础巩固","frequency":1},{"word":"ice","phonetic":"ais","translation":"n. 冰, 冰淇淋, 糖衣, 冷若冰霜, 矜持, 贿赂；vt. 使结冰, 冰镇, 覆以糖衣","definition":"n. water frozen in the solid state","pos":"n. 名词","level":"基础巩固","frequency":1},{"word":"instead","phonetic":"in'sted","translation":"adv. 作为替代, 反而","definition":"r in place of, or as an alternative to","pos":"adv. 副词","level":"基础巩固","frequency":1},{"word":"jump","phonetic":"dʒʌmp","translation":"n. 跳跃, 跳动, 暴涨, 惊跳；vt. 跳跃, 跃过, 突升, 使跳跃","definition":"n. a sudden and decisive increase","pos":"n. 名词","level":"基础巩固","frequency":1},{"word":"kick","phonetic":"kik","translation":"n. 踢, 反冲, 后座力, 凹底；vi. 踢, 反抗, 反冲","definition":"n. the act of delivering a blow with the foot","pos":"n. 名词","level":"基础巩固","frequency":1},{"word":"notice","phonetic":"'nәutis","translation":"n. 注意, 布告, 通知, 预告, 短评；vt. 注意, 通知, 评论, 提及, 关注","definition":"n. an announcement containing information about an event","pos":"n. 名词","level":"基础巩固","frequency":1},{"word":"object","phonetic":"'ɒbdʒekt","translation":"n. 物体, 目标, 目的, 对象, 宾语, 客体；vi. 反对, 抱反感","definition":"n. a tangible and visible entity; an entity that can cast a shadow","pos":"n. 名词","level":"基础巩固","frequency":1},{"word":"package","phonetic":"'pækidʒ","translation":"n. 包裹, 套装软件, 包, 包装用物, 程序包；vt. 包装, 打包","definition":"n. a collection of things wrapped or boxed together","pos":"n. 名词","level":"基础巩固","frequency":1},{"word":"popular","phonetic":"'pɒpjulә","translation":"a. 通俗的, 流行的, 受欢迎的, 大众的, 人民的, 普及的","definition":"a. regarded with great favor, approval, or affection especially by the general public","pos":"adj. 形容词","level":"基础巩固","frequency":1},{"word":"sad","phonetic":"sæd","translation":"a. 忧愁的, 悲哀的","definition":"a. experiencing or showing sorrow or unhappiness","pos":"adj. 形容词","level":"基础巩固","frequency":1},{"word":"safe","phonetic":"seif","translation":"n. 保险箱, 冷藏室；a. 安全的, 可靠的, 平安的, 稳健的, 有把握的","definition":"n. strongbox where valuables can be safely kept","pos":"n. 名词","level":"基础巩固","frequency":1},{"word":"safety","phonetic":"'seifti","translation":"n. 安全, 保险, 平安, 保安设备；vt. 保护, 防护","definition":"n. the state of being certain that adverse effects will not be caused by some agent under defined conditions","pos":"n. 名词","level":"基础巩固","frequency":1},{"word":"sight","phonetic":"sait","translation":"n. 景观, 视力, 眼界, 阅读, 见解, 意见；vt. 看见, 瞄准","definition":"n. an instance of visual perception","pos":"n. 名词","level":"基础巩固","frequency":1},{"word":"soft","phonetic":"sɒft","translation":"a. 软的, 温和的, 柔和的, 柔滑的, 温柔的, 软弱的, 坡度小的, 笨的, 纸币的；n. 柔软的东西, 笨人, 纸币","definition":"a. yielding readily to pressure or weight","pos":"adj. 形容词","level":"基础巩固","frequency":1},{"word":"spirit","phonetic":"'spirit","translation":"n. 精神, 心灵, 灵魂, 态度, 志气, 人格, 情绪, 心情, 烈酒；vt. 诱拐, 鼓励, 鼓舞","definition":"n. the vital principle or animating force within living things","pos":"n. 名词","level":"基础巩固","frequency":1},{"word":"spring","phonetic":"spriŋ","translation":"n. 春天, 弹簧, 跳跃, 弹性, 活力, 泉, 源泉；a. 春天的","definition":"n. the season of growth","pos":"n. 名词","level":"基础巩固","frequency":1},{"word":"suppose","phonetic":"sә'pәuz","translation":"vt. 推想, 假设, 以为, 想像, 假定；vi. 料想","definition":"v. express a supposition","pos":"vt. 及物动词","level":"基础巩固","frequency":1},{"word":"useful","phonetic":"'ju:sful","translation":"a. 有用的, 有益的；[机] 有用的, 有效的","definition":"a. being of use or service","pos":"adj. 形容词","level":"基础巩固","frequency":1},{"word":"warm","phonetic":"wɒ:m","translation":"a. 暖和的, 暖的, 温暖的, 热烈的, 兴奋的, 激烈的, 多情的, 色情的；vt. 使温暖, 弄热, 使兴奋, 使充满仇恨","definition":"v. get warm or warmer","pos":"adj. 形容词","level":"基础巩固","frequency":1},{"word":"weak","phonetic":"wi:k","translation":"a. 不牢固的, 弱的, 虚弱的, 软弱的, 无力的, 无权力的, (论据等)不充分的","definition":"a. wanting in physical strength","pos":"adj. 形容词","level":"基础巩固","frequency":1},{"word":"wind","phonetic":"wind","translation":"n. 风, 气息, 气味, 呼吸, 风声, 趋势, 空谈, 卷绕, 弯曲；vt. 使通风, 嗅出, 使喘气, 吹号角, 上发条, 缠绕, 包, 绞起, 吊起, 使弯曲, 使迂回","definition":"n. air moving (sometimes with considerable force) from an area of high pressure to an area of low pressure","pos":"n. 名词","level":"基础巩固","frequency":1},{"word":"aid","phonetic":"eid","translation":"n. 帮助, 外援, 助手；vt. 援助, 帮助, 有助于","definition":"n. a resource","pos":"n. 名词","level":"基础巩固","frequency":1},{"word":"bite","phonetic":"bait","translation":"n. 咬, 一口；v. 咬, 刺痛, 穿透","definition":"n. a wound resulting from biting by an animal or a person","pos":"n. 名词","level":"本龄重点","frequency":1},{"word":"delicate","phonetic":"'delikәt","translation":"a. 细致优雅的, 微妙的, 美味的","definition":"a. exquisitely fine and subtle and pleasing; susceptible to injury","pos":"adj. 形容词","level":"本龄重点","frequency":3},{"word":"kindly","phonetic":"'kaindli","translation":"a. 和蔼的, 温和的, 爽快的；adv. 温和地, 亲切地","definition":"s. pleasant and agreeable","pos":"adj. 形容词","level":"拓展挑战","frequency":3},{"word":"working","phonetic":"'wә:kiŋ","translation":"n. 工作, 运转, 劳动；a. 工作的, 劳动的, 经营的, 抽搐的, 运转的","definition":"n. a mine or quarry that is being or has been worked","pos":"n. 名词","level":"基础巩固","frequency":1},{"word":"lively","phonetic":"'laivli","translation":"a. 活泼的, 鲜明的, 生动的","definition":"a. full of life and energy","pos":"adj. 形容词","level":"本龄重点","frequency":2},{"word":"alarm","phonetic":"ә'lɑ:m","translation":"n. 惊恐, 警报, 警钟；vt. 使惊恐, 警告","definition":"n. fear resulting from the awareness of danger","pos":"n. 名词","level":"本龄重点","frequency":2},{"word":"beginning","phonetic":"bi'giniŋ","translation":"n. 开始","definition":"n. the event consisting of the start of something","pos":"n. 名词","level":"基础巩固","frequency":2},{"word":"easily","phonetic":"'i:zili","translation":"adv. 容易地, 轻易地, 流利地","definition":"r. with ease (`easy' is sometimes used informally for `easily')","pos":"adv. 副词","level":"基础巩固","frequency":2},{"word":"quietly","phonetic":"'kwaiәtli","translation":"adv. 安静地, 沉着地, 秘密地","definition":"r. with little or no sound","pos":"adv. 副词","level":"基础巩固","frequency":4},{"word":"reward","phonetic":"ri'wɒ:d","translation":"n. 报酬, 酬谢, 赏金；vt. 奖赏, 酬谢, 给...应有报应","definition":"n. payment made in return for a service rendered","pos":"n. 名词","level":"基础巩固","frequency":2},{"word":"angry","phonetic":"'æŋgri","translation":"a. 生气的, 愤怒的","definition":"a. feeling or showing anger","pos":"adj. 形容词","level":"基础巩固","frequency":1},{"word":"anywhere","phonetic":"'enihwєә","translation":"adv. 无论何处","definition":"r. at or in or to any place; (`anyplace' is used informally for `anywhere')","pos":"adv. 副词","level":"基础巩固","frequency":1},{"word":"bell","phonetic":"bel","translation":"n. 铃, 钟","definition":"n. a hollow device made of metal that makes a ringing sound when struck","pos":"n. 名词","level":"基础巩固","frequency":1},{"word":"bowl","phonetic":"bәul","translation":"n. 碗, 木球, 大酒杯；v. 滚木球, 快而稳地行驶","definition":"n. a round vessel that is open at the top; used chiefly for holding food or liquids;","pos":"n. 名词","level":"基础巩固","frequency":1},{"word":"bread","phonetic":"bred","translation":"n. 面包, 生计, 食物；vt. 裹以面包屑","definition":"n. food made from dough of flour or meal and usually raised with yeast or baking powder and then baked","pos":"n. 名词","level":"基础巩固","frequency":1},{"word":"cap","phonetic":"kæp","translation":"n. 盖子, 帽子；vt. 戴帽子, 覆盖, 胜过","definition":"n. a tight-fitting headdress","pos":"n. 名词","level":"基础巩固","frequency":1},{"word":"coat","phonetic":"kәut","translation":"n. 外套；vt. 外面覆盖, 给...穿外套","definition":"n. an outer garment that has sleeves and covers the body from shoulder down; worn outdoors","pos":"n. 名词","level":"基础巩固","frequency":1},{"word":"comfortable","phonetic":"'kʌmfәtәbl","translation":"a. 舒服的, 轻松的；n. 盖被","definition":"a. providing or experiencing physical well-being or relief (`comfy' is informal)","pos":"adj. 形容词","level":"基础巩固","frequency":1},{"word":"conversation","phonetic":".kɒnvә'seiʃәn","translation":"n. 会话, 说话, 交谈","definition":"n. the use of speech for informal exchange of views or ideas or information etc.","pos":"n. 名词","level":"基础巩固","frequency":1},{"word":"friendly","phonetic":"'frendli","translation":"a. 友好的, 亲切的, 互助的；adv. 友善地, 温和地","definition":"n. troops belonging to or allied with your own military forces","pos":"adj. 形容词","level":"基础巩固","frequency":1},{"word":"hide","phonetic":"haid","translation":"n. 兽皮, 迹象, 躲藏处；vt. 藏, 隐瞒, 遮避, 剥...的皮, 隐藏","definition":"n. the dressed skin of an animal (especially a large animal)","pos":"n. 名词","level":"基础巩固","frequency":1},{"word":"hill","phonetic":"hil","translation":"n. 小山, 丘陵, 小土堆；vt. 作成土堆, 堆成小丘","definition":"n. a local and well-defined elevation of the land","pos":"n. 名词","level":"基础巩固","frequency":1},{"word":"knee","phonetic":"ni:","translation":"n. 膝, 膝盖；vt. 膝行, 用膝盖碰","definition":"n. hinge joint in the human leg connecting the tibia and fibula with the femur and protected in front by the patella","pos":"n. 名词","level":"基础巩固","frequency":1},{"word":"mad","phonetic":"mæd","translation":"a. 疯狂的, 发疯的, 生气的, 愚蠢的, 狂欢的；n. 狂怒","definition":"s roused to anger","pos":"adj. 形容词","level":"基础巩固","frequency":1},{"word":"meat","phonetic":"mi:t","translation":"n. 肉, 餐, 食物","definition":"n. the flesh of animals (including fishes and birds and snails) used as food","pos":"n. 名词","level":"基础巩固","frequency":1},{"word":"moon","phonetic":"mu:n","translation":"n. 月亮, 月球, 月光；vi. 闲荡","definition":"n. the natural satellite of the Earth","pos":"n. 名词","level":"基础巩固","frequency":1},{"word":"neck","phonetic":"nek","translation":"n. 脖子, 衣领, 颈；vi. 拥抱, 拥吻, 收缩","definition":"n. the part of an organism (human or animal) that connects the head to the rest of the body","pos":"n. 名词","level":"基础巩固","frequency":1},{"word":"pale","phonetic":"peil","translation":"n. 栅栏, 界线, 范围；a. 苍白的, 暗淡的, 无力的","definition":"v. turn pale, as if in fear","pos":"n. 名词","level":"基础巩固","frequency":1},{"word":"pleasant","phonetic":"'pleznt","translation":"a. 愉快的, 可爱的, 活泼的, 亲切的","definition":"a. affording pleasure; being in harmony with your taste or likings","pos":"adj. 形容词","level":"基础巩固","frequency":1},{"word":"proud","phonetic":"praud","translation":"a. 骄傲的, 自大的, 自豪的, 辉煌的, 壮丽的","definition":"a. feeling self-respect or pleasure in something by which you measure your self-worth; or being a reason for pride","pos":"adj. 形容词","level":"基础巩固","frequency":1},{"word":"regret","phonetic":"ri'gret","translation":"n. 遗憾, 后悔, 悔恨, 抱歉, 歉意；vt. 为...感到遗憾, 后悔, 惋惜, 懊悔, 抱歉","definition":"v. feel sad about the loss or absence of","pos":"n. 名词","level":"本龄重点","frequency":1},{"word":"ring","phonetic":"riŋ","translation":"n. 环, 环形物, 拳击场, 戒指, 角逐, 小集团, 铃声, 钟声, 声调；vt. 包围, 套住, 按铃, 敲钟","definition":"n. a characteristic sound","pos":"n. 名词","level":"基础巩固","frequency":1},{"word":"sick","phonetic":"sik","translation":"n. 病人；a. 不舒服, 有病的, 恶心的, 厌恶的, 渴望的, 病态的","definition":"n. people who are sick","pos":"n. 名词","level":"基础巩固","frequency":1},{"word":"somewhere","phonetic":"'sʌmhwєә","translation":"adv. 到某处, 在某处","definition":"n. an indefinite or unknown location","pos":"adv. 副词","level":"基础巩固","frequency":1},{"word":"sweet","phonetic":"swi:t","translation":"n. 甜蜜, 糖果, 情人；a. 甜的, 芳香的, 悦耳的, 漂亮的, 和蔼的, 不咸的, 灵活的, 轻快的","definition":"n. English phonetician; one of the founders of modern phonetics (1845-1912)","pos":"n. 名词","level":"基础巩固","frequency":1},{"word":"tall","phonetic":"tɒ:l","translation":"a. 高的, 长的, 夸大的；adv. 夸大地","definition":"n. a garment size for a tall person","pos":"adj. 形容词","level":"基础巩固","frequency":1},{"word":"text","phonetic":"tekst","translation":"n. 文本, 正文, 课文, 主题, 圣经文句, 乐谱","definition":"n. the words of something written","pos":"n. 名词","level":"基础巩固","frequency":1},{"word":"thick","phonetic":"θik","translation":"a. 厚的, 粗壮的, 浓的, 迟钝的, 浑浊的, 多雾的, 过分的, 口齿不清的；adv. 厚地, 密地, 浓浓地","definition":"a. not thin; of a specific thickness or of relatively great extent from one surface to the opposite usually in the smallest of the three solid dimensions","pos":"adj. 形容词","level":"基础巩固","frequency":1},{"word":"wet","phonetic":"wet","translation":"n. 湿气, 潮湿, 水分, 雨天；a. 湿的, 潮的, 搞错的, 下雨的, 反对禁酒的","definition":"v. cause to become wet","pos":"n. 名词","level":"基础巩固","frequency":1},{"word":"ahead","phonetic":"ә'hed","translation":"a. 领先的, 预先的, 向前的；adv. 领先, 预先, 向前, 胜于, 在前面, 在将来","definition":"s. having the leading position or higher score in a contest","pos":"adj. 形容词","level":"基础巩固","frequency":1},{"word":"appearance","phonetic":"ә'piәrәns","translation":"n. 出现, 露面, 外观, 外表, 出版","definition":"n. outward or visible aspect of a person or thing","pos":"n. 名词","level":"基础巩固","frequency":1},{"word":"argument","phonetic":"'ɑ:gjumәnt","translation":"n. 争论, 论证, 论据, 自变量","definition":"n. a fact or assertion offered as evidence that something is true","pos":"n. 名词","level":"基础巩固","frequency":1},{"word":"attract","phonetic":"ә'trækt","translation":"vt. 吸引, 诱惑；vi. 有吸引力","definition":"v. direct toward itself or oneself by means of some psychological power or physical attributes","pos":"vt. 及物动词","level":"基础巩固","frequency":1},{"word":"band","phonetic":"bænd","translation":"n. 带子, 队, 乐队；v. 联合, 结合","definition":"n. instrumentalists not including string players","pos":"n. 名词","level":"基础巩固","frequency":1},{"word":"broad","phonetic":"brɒ:d","translation":"a. 宽广的, 辽阔的, 广大的, 显著的；adv. 宽阔地","definition":"n. slang term for a woman","pos":"adj. 形容词","level":"基础巩固","frequency":1},{"word":"cast","phonetic":"kɑ:st. kæst","translation":"n. 演员阵容, 投掷, 铸件, 预测, 特性；vt. 投, 掷, 抛, 脱落, 铸, 使弯曲, 计算","definition":"n. the actors in a play","pos":"n. 名词","level":"基础巩固","frequency":1},{"word":"confidence","phonetic":"'kɒnfidәns","translation":"n. 信心；[电] 可靠","definition":"n. a feeling of trust (in someone or something)","pos":"n. 名词","level":"基础巩固","frequency":1},{"word":"delay","phonetic":"di'lei","translation":"n. 耽搁, 迟滞；v. 耽搁, 延迟","definition":"n. time during which some action is awaited","pos":"n. 名词","level":"基础巩固","frequency":1},{"word":"directly","phonetic":"di'rektli, dai'rektli","translation":"adv. 径直地, 直接地, 直率地, 正好地, 直截了当地, (非正式)立即, 马上；conj. 一...(就...), 一当...就...","definition":"r. without deviation","pos":"adv. 副词","level":"基础巩固","frequency":3},{"word":"entire","phonetic":"in'taiә","translation":"n. 整个, 全部；a. 全体的, 完全的, 全部的","definition":"s. constituting the full quantity or extent; complete","pos":"n. 名词","level":"基础巩固","frequency":1},{"word":"escape","phonetic":"i'skeip","translation":"n. 逃亡, 避难设备, 逃跑；vi. 逃脱, 避开, 溜走","definition":"n. the act of escaping physically","pos":"n. 名词","level":"基础巩固","frequency":1},{"word":"fully","phonetic":"'fuli","translation":"adv. 十分地, 完全地, 充分地","definition":"r. to the greatest degree or extent; completely or entirely; (`full' in this sense is used as a combining form)","pos":"adv. 副词","level":"基础巩固","frequency":1},{"word":"leading","phonetic":"'li:diŋ","translation":"n. 领导, 指挥, 神示, 铅板；a. 领导的, 主要的, 在前的","definition":"s. indicating the most important performer or role","pos":"n. 名词","level":"基础巩固","frequency":1},{"word":"length","phonetic":"leŋθ","translation":"n. 长度, 长, 期间, 一段","definition":"n. the linear extent in space from one end to the other; the longest dimension of something that is fixed in place","pos":"n. 名词","level":"基础巩固","frequency":1},{"word":"possibly","phonetic":"'pɒsәbli","translation":"adv. 可能, 也许","definition":"r. by chance","pos":"adv. 副词","level":"基础巩固","frequency":1},{"word":"prefer","phonetic":"pri'fә:","translation":"vt. 宁可, 较喜欢, 提出","definition":"v. like better; value more highly","pos":"vt. 及物动词","level":"基础巩固","frequency":1},{"word":"sharp","phonetic":"ʃɑ:p","translation":"n. 半升音调, 利刃, 骗子；a. 锋利的, 明显的, 敏锐的, 急剧的, 尖刻的, 严厉的, 刺耳的, 精明的","definition":"n. a musical notation indicating one half step higher than the note named","pos":"n. 名词","level":"基础巩固","frequency":1},{"word":"slip","phonetic":"slip","translation":"n. 滑, 滑行, 事故, 溜, 差错, 滑台, 下降, 插条, 后裔, 板条, 瘦长的年轻人；vi. 滑动, 滑倒, 失足, 溜走, 滑落, 犯错, 变坏","definition":"n. a minor inadvertent mistake usually observed in speech or writing or in small accidents or memory lapses etc.","pos":"n. 名词","level":"基础巩固","frequency":1},{"word":"straight","phonetic":"streit","translation":"n. 直线, 直；a. 直的, 笔直的, 正直的, 直接的, 连续的, 整齐的","definition":"n. a poker hand with 5 consecutive cards (regardless of suit)","pos":"n. 名词","level":"基础巩固","frequency":1},{"word":"tend","phonetic":"tend","translation":"vi. 走向, 有某种的倾向, 易于, 照顾, 注意；vt. 照料, 护理","definition":"v. have a tendency or disposition to do or be something; be inclined","pos":"vi. 不及物动词","level":"基础巩固","frequency":1},{"word":"violence","phonetic":"'vaiәlәns","translation":"n. 猛烈, 暴力, 暴虐, 暴行","definition":"n. an act of aggression (as one against a person who resists)","pos":"n. 名词","level":"基础巩固","frequency":1},{"word":"willing","phonetic":"'wiliŋ","translation":"a. 乐意的, 自愿的, 甘愿的","definition":"a. disposed or inclined toward","pos":"adj. 形容词","level":"基础巩固","frequency":1},{"word":"aloud","phonetic":"ә'laud","translation":"adv. 出声地, 大声地","definition":"r. using the voice; not silently","pos":"adv. 副词","level":"拓展挑战","frequency":2},{"word":"burden","phonetic":"'bә:dn","translation":"n. 负担, 重载, 担子, 责任；vt. 装货于, 烦扰, 使负担","definition":"n. an onerous or difficult concern","pos":"n. 名词","level":"基础巩固","frequency":3},{"word":"given","phonetic":"'givәn","translation":"a. 赠予的, 沉溺的, 约定的；give的过去分词","definition":"n. an assumption that is taken for granted","pos":"adj. 形容词","level":"基础巩固","frequency":3},{"word":"leap","phonetic":"li:p","translation":"n. 跳跃, 剧增, 急变, 被越过之物；vi. 跳跃, 突然经过","definition":"n. a light, self-propelled movement upwards or forwards","pos":"n. 名词","level":"本龄重点","frequency":3},{"word":"ought","phonetic":"ɒ:t","translation":"aux. 应该, 大概；n. 责任","definition":"n. & adv. See Aught.","pos":"重点词","level":"基础巩固","frequency":3},{"word":"amusing","phonetic":"ә'mju:ziŋ","translation":"a. 有趣的, 引人发笑的","definition":"s. providing enjoyment; pleasantly entertaining","pos":"adj. 形容词","level":"拓展挑战","frequency":2},{"word":"horn","phonetic":"hɒ:n","translation":"n. 角, 角质, 喇叭, 号角；a. 角制的","definition":"n. a noisemaker (as at parties or games) that makes a loud noise when you blow through it","pos":"n. 名词","level":"本龄重点","frequency":2},{"word":"shiny","phonetic":"'ʃaini","translation":"a. 有光泽的, 发光的, 辉煌的, 磨光的, 磨损的","definition":"s reflecting light","pos":"adj. 形容词","level":"本龄重点","frequency":2},{"word":"upwards","phonetic":"'ʌpwәdz","translation":"adv. 以上, 向上","definition":"r spatially or metaphorically from a lower to a higher position","pos":"adv. 副词","level":"本龄重点","frequency":2},{"word":"hungry","phonetic":"'hʌŋgi","translation":"a. 饥饿的, 荒年的, 渴望的, 不毛的","definition":"a. feeling hunger; feeling a need or desire to eat food","pos":"adj. 形容词","level":"本龄重点","frequency":1},{"word":"polite","phonetic":"pә'lait","translation":"a. 有礼貌的, 文雅的, 客气的, 有教养的","definition":"a. showing regard for others in manners, speech, behavior, etc.","pos":"adj. 形容词","level":"本龄重点","frequency":1},{"word":"silly","phonetic":"'sili","translation":"a. 愚蠢的, 糊涂的","definition":"n. a word used for misbehaving children","pos":"adj. 形容词","level":"基础巩固","frequency":1},{"word":"stranger","phonetic":"'streindʒә","translation":"n. 陌生人, 门外汉","definition":"n. anyone who does not belong in the environment in which they are found","pos":"n. 名词","level":"基础巩固","frequency":1},{"word":"summit","phonetic":"'sʌmit","translation":"n. 顶点, 最高阶层, 最高级会议；a. 政府首脑的, 最高级的","definition":"n. a meeting of heads of governments","pos":"n. 名词","level":"本龄重点","frequency":2},{"word":"admire","phonetic":"әd'maiә","translation":"vt. 赞美, 钦佩, 爱慕；vi. 称赞, 惊奇","definition":"v. feel admiration for","pos":"vt. 及物动词","level":"本龄重点","frequency":1},{"word":"afterwards","phonetic":"'ɑ:ftәwәdz","translation":"adv. 然后, 后来","definition":"r happening at a time subsequent to a reference time","pos":"adv. 副词","level":"基础巩固","frequency":1},{"word":"anxious","phonetic":"'æŋʃәs","translation":"a. 忧虑的, 发愁的, 渴望的","definition":"s. eagerly desirous","pos":"adj. 形容词","level":"基础巩固","frequency":1},{"word":"bargain","phonetic":"'bɑ:gin","translation":"n. 交易, 买卖协定, 特价商品；v. 讲价, 交易","definition":"n. an agreement between parties (usually arrived at after discussion) fixing obligations of each","pos":"n. 名词","level":"本龄重点","frequency":1},{"word":"brilliant","phonetic":"'briljәnt","translation":"a. 光辉的, 灿烂的, 有才气的；[机] 亮的","definition":"s. of surpassing excellence","pos":"adj. 形容词","level":"基础巩固","frequency":1},{"word":"cottage","phonetic":"'kɒtidʒ","translation":"n. 小屋, 茅舍","definition":"n a small house with a single story","pos":"n. 名词","level":"基础巩固","frequency":1},{"word":"cure","phonetic":"kjuә","translation":"n. 治疗, 治愈, 治疗法；vt. 治疗, 治愈, 改正, 腌制, 加工处理, 使硫化","definition":"v. prepare by drying, salting, or chemical processing in order to preserve","pos":"n. 名词","level":"本龄重点","frequency":1},{"word":"delighted","phonetic":"di'laitid","translation":"a. 高兴的, 快乐的","definition":"s. greatly pleased","pos":"adj. 形容词","level":"本龄重点","frequency":1},{"word":"enthusiasm","phonetic":"in'θju:ziæzәm","translation":"n. 巨大的热情, 热心","definition":"n. a feeling of excitement","pos":"n. 名词","level":"基础巩固","frequency":1},{"word":"exception","phonetic":"ik'sepʃәn","translation":"n. 例外, 除外, 异议","definition":"n. a deliberate act of omission","pos":"n. 名词","level":"基础巩固","frequency":1},{"word":"familiar","phonetic":"fә'miljә","translation":"a. 熟悉的, 常见的, 亲密的；n. 熟友, 常客","definition":"n. a person attached to the household of a high official (as a pope or bishop) who renders service in return for support","pos":"adj. 形容词","level":"基础巩固","frequency":1},{"word":"fault","phonetic":"fɒ:lt","translation":"n. 过错, 故障, 毛病；vt. 挑剔","definition":"n. (geology) a crack in the earth's crust resulting from the displacement of one side with respect to the other","pos":"n. 名词","level":"基础巩固","frequency":1},{"word":"frame","phonetic":"freim","translation":"n. 框, 结构, 体格；vt. 构成, 设计, 制定, 使适合, 陷害","definition":"n. the framework for a pair of eyeglasses","pos":"n. 名词","level":"基础巩固","frequency":1},{"word":"happiness","phonetic":"'hæpinis","translation":"n. 快乐, 幸运, 适当","definition":"n. state of well-being characterized by emotions ranging from contentment to intense joy","pos":"n. 名词","level":"本龄重点","frequency":3},{"word":"hunt","phonetic":"hʌnt","translation":"n. 狩猎, 追捕, 搜寻, 猎区；vt. 狩猎, 打猎, 搜索","definition":"n. Englishman and Pre-Raphaelite painter (1827-1910)","pos":"n. 名词","level":"本龄重点","frequency":1},{"word":"impression","phonetic":"im'preʃәn","translation":"n. 印象, 意念, 盖印, 印记, 印数, 底色, 效果","definition":"n. a vague idea in which some confidence is placed","pos":"n. 名词","level":"基础巩固","frequency":1},{"word":"keen","phonetic":"ki:n","translation":"a. 锋利的, 敏锐的, 强烈的, 敏捷的, 热心的, 渴望的；n. 挽歌, 痛哭","definition":"n. a funeral lament sung with loud wailing","pos":"adj. 形容词","level":"基础巩固","frequency":1},{"word":"living","phonetic":"'liviŋ","translation":"n. 生活, 生计, 生存；a. 活的, 逼真的, 现存的","definition":"n. people who are still living","pos":"n. 名词","level":"基础巩固","frequency":1},{"word":"moreover","phonetic":"mɒ:'әuvә","translation":"adv. 而且, 此外","definition":"r in addition; furthermore, their quality is improving\"; moreover, mice nested there\"","pos":"adv. 副词","level":"基础巩固","frequency":1},{"word":"mount","phonetic":"maunt","translation":"n. 乘骑用马, 框, 衬纸, 山；vi. 乘马, 爬上, 增长","definition":"n. a mounting consisting of a piece of metal (as in a ring or other jewelry) that holds a gem in place","pos":"n. 名词","level":"基础巩固","frequency":1},{"word":"persuade","phonetic":"pә'sweid","translation":"vt. 劝, 使相信, 恳求, 敦促, 说服；vi. 劝服, 被说服","definition":"v. cause somebody to adopt a certain position, belief, or course of action; twist somebody's arm","pos":"vt. 及物动词","level":"基础巩固","frequency":1},{"word":"rear","phonetic":"riә","translation":"n. 后面, 背后, 后方；a. 后面的, 背面的, 后方的","definition":"n. the back of a military formation or procession","pos":"n. 名词","level":"本龄重点","frequency":1},{"word":"rescue","phonetic":"'reskju:","translation":"n. 援救, 解救, 营救；vt. 援救, 救出, 营救","definition":"n. recovery or preservation from loss or danger","pos":"n. 名词","level":"本龄重点","frequency":1},{"word":"satisfied","phonetic":"'sætisfaiәd","translation":"a. 感到满意的","definition":"s. filled with satisfaction","pos":"adj. 形容词","level":"基础巩固","frequency":1},{"word":"sensible","phonetic":"'sensәbl","translation":"a. 有感觉的, 敏感的, 明智的","definition":"a. able to feel or perceive","pos":"adj. 形容词","level":"基础巩固","frequency":1},{"word":"shell","phonetic":"ʃel","translation":"n. 贝壳, 壳, 外形, 炮弹；vt. 去壳, 脱落, 炮轰","definition":"n. ammunition consisting of a cylindrical metal casing containing an explosive charge and a projectile; fired from a large gun","pos":"n. 名词","level":"基础巩固","frequency":1},{"word":"stir","phonetic":"stә:","translation":"n. 骚动, 轰动, 搅动, 监狱；vt. 移动, 摇动, 激起, 惹起, 搅拌","definition":"n. a prominent or sensational but short-lived news event","pos":"n. 名词","level":"基础巩固","frequency":1},{"word":"truly","phonetic":"'tru:li","translation":"adv. 真实地, 不假","definition":"r. in accordance with truth or fact or reality","pos":"adv. 副词","level":"基础巩固","frequency":1},{"word":"unexpected","phonetic":".ʌnik'spektid","translation":"a. 料想不到的, 突然的, 意外的","definition":"a. not expected or anticipated","pos":"adj. 形容词","level":"本龄重点","frequency":1},{"word":"valuable","phonetic":"'væljuәbl","translation":"a. 有价值的, 贵重的, 宝贵的, 可估价的","definition":"n. something of value","pos":"adj. 形容词","level":"基础巩固","frequency":1},{"word":"accord","phonetic":"ә'kɒ:d","translation":"n. 一致, 调和, 协定；vt. 给与, 使一致","definition":"n. concurrence of opinion","pos":"n. 名词","level":"拓展挑战","frequency":1},{"word":"doorway","phonetic":"'dɒ:wei","translation":"n. 门口, 途径","definition":"n. the entrance (the space in a wall) through which you enter or leave a room or building; the space that a door can close","pos":"n. 名词","level":"本龄重点","frequency":3},{"word":"dragon","phonetic":"'drægәn","translation":"n. 龙, 凶暴的人","definition":"n. a creature of Teutonic mythology; usually represented as breathing fire and having a reptilian body and sometimes wings","pos":"n. 名词","level":"本龄重点","frequency":3},{"word":"midst","phonetic":"midst","translation":"n. 中间；prep. 在...中间","definition":"n. the location of something surrounded by other things","pos":"n. 名词","level":"本龄重点","frequency":3},{"word":"projection","phonetic":"prә'dʒekʃәn","translation":"n. 发射, 计划, 突出部分, 设计, 推测","definition":"n. a prediction made by extrapolating from past observations","pos":"n. 名词","level":"本龄重点","frequency":3},{"word":"ribbon","phonetic":"'ribәn","translation":"n. 缎带, 色带, 带状物；vt. 用丝带装饰, 把...撕成条状","definition":"n. any long object resembling a thin line","pos":"n. 名词","level":"本龄重点","frequency":3},{"word":"rod","phonetic":"rɒd","translation":"n. 竿, 笞鞭, 小枝","definition":"n. a long thin implement made of metal or wood","pos":"n. 名词","level":"本龄重点","frequency":3},{"word":"broken","phonetic":"'brәukәn","translation":"a. 坏掉的, 打破的, 断掉的；break的过去分词","definition":"a. physically and forcibly separated into pieces or cracked or split","pos":"adj. 形容词","level":"基础巩固","frequency":2},{"word":"noon","phonetic":"nu:n","translation":"n. 正午, 中午, 全盛期","definition":"n. the middle of the day","pos":"n. 名词","level":"本龄重点","frequency":2},{"word":"supper","phonetic":"'sʌpә","translation":"n. 晚餐","definition":"n. a light evening meal; served in early evening if dinner is at midday or served late in the evening at bedtime","pos":"n. 名词","level":"本龄重点","frequency":2},{"word":"forth","phonetic":"fɒ:θ","translation":"adv. 往前, 以后, 向外","definition":"n. a river in southern Scotland that flows eastward to the Firth of Forth","pos":"adv. 副词","level":"基础巩固","frequency":2},{"word":"affection","phonetic":"ә'fekʃәn","translation":"n. 影响, 病, 喜爱, 情感, 倾向","definition":"n. a positive feeling of liking","pos":"n. 名词","level":"本龄重点","frequency":1},{"word":"anybody","phonetic":"'enibɒdi","translation":"pron. 任何人；n. 重要人物","definition":"n. Any one out of an indefinite number of persons; anyone;","pos":"重点词","level":"基础巩固","frequency":1},{"word":"climbing","phonetic":"'klaimiŋ","translation":"a. 攀缘而登的, 上升的；n. 攀登","definition":"n an event that involves rising to a higher point (as in altitude or temperature or intensity etc.)","pos":"adj. 形容词","level":"拓展挑战","frequency":1},{"word":"closed","phonetic":"klәuzd","translation":"a. 关闭的, 限于少数人的","definition":"a. not open or affording passage or access","pos":"adj. 形容词","level":"本龄重点","frequency":1},{"word":"crowded","phonetic":"'kraudid","translation":"a. 拥挤的, 塞满的","definition":"a. overfilled or compacted or concentrated","pos":"adj. 形容词","level":"本龄重点","frequency":1},{"word":"diamond","phonetic":"'daiәmәnd","translation":"n. 钻石, 菱形","definition":"n. a transparent piece of diamond that has been cut and polished and is valued as a precious gem","pos":"n. 名词","level":"本龄重点","frequency":1},{"word":"drunk","phonetic":"drʌŋk","translation":"a. 喝醉了的；drink的过去式","definition":"n. someone who is intoxicated","pos":"adj. 形容词","level":"本龄重点","frequency":1},{"word":"ending","phonetic":"'endiŋ","translation":"n. 终止, 终了, 收场","definition":"n. the end of a word (a suffix or inflectional ending or final morpheme)","pos":"n. 名词","level":"本龄重点","frequency":1},{"word":"excitement","phonetic":"ik'saitmәnt","translation":"n. 刺激, 兴奋","definition":"n. the state of being emotionally aroused and worked up","pos":"n. 名词","level":"基础巩固","frequency":1},{"word":"faint","phonetic":"feint","translation":"n. 昏厥, 昏倒；a. 模糊的, 微弱的, 无力的","definition":"n. a spontaneous loss of consciousness caused by insufficient blood to the brain","pos":"n. 名词","level":"本龄重点","frequency":1},{"word":"finished","phonetic":"'finiʃt","translation":"a. 完成的, 完结的, 精巧的, 完美的","definition":"a. (of materials or goods) brought to the desired final state","pos":"adj. 形容词","level":"拓展挑战","frequency":1},{"word":"moving","phonetic":"'mu:viŋ","translation":"a. 动人的, 令人感动的, 鼓动的, 原动的, [无比较级]活动的, 转动的","definition":"a. in motion","pos":"adj. 形容词","level":"拓展挑战","frequency":1},{"word":"passing","phonetic":"'pæsiŋ","translation":"n. 通过, 逝去, 死, 流逝；a. 经过的, 流逝的, 目前的, 短暂的, 及格的, 仓促的","definition":"n. euphemistic expressions for death","pos":"n. 名词","level":"本龄重点","frequency":1},{"word":"possession","phonetic":"pә'zeʃәn","translation":"n. 拥有, 占有, 所有, 财产, 领土, 领地, 自制, 着迷","definition":"n. the act of having and controlling property","pos":"n. 名词","level":"基础巩固","frequency":1},{"word":"practically","phonetic":"'præktikli","translation":"adv. 几乎, 差不多, 事实上","definition":"r. almost; nearly","pos":"adv. 副词","level":"本龄重点","frequency":1},{"word":"repeated","phonetic":"ri'pi:tid","translation":"a. 重复的, 再三的","definition":"v to say, state, or perform again","pos":"adj. 形容词","level":"拓展挑战","frequency":1},{"word":"satisfaction","phonetic":".sætis'fækʃәn","translation":"n. 满足, 满意, 快事, 赔偿, 赎罪, 报仇的机会","definition":"n. the contentment one feels when one has fulfilled a desire, need, or expectation","pos":"n. 名词","level":"基础巩固","frequency":1},{"word":"suffering","phonetic":"'sʌfәriŋ","translation":"n. 苦难, 受苦","definition":"n. misery resulting from affliction","pos":"n. 名词","level":"本龄重点","frequency":1},{"word":"unusually","phonetic":"ʌn'ju:ʒәli","translation":"adv. 不寻常地, 异乎寻常地, (非正式)非常","definition":"r. to a remarkable degree or extent","pos":"adv. 副词","level":"拓展挑战","frequency":1},{"word":"wander","phonetic":"'wɒndә","translation":"vi. 游荡, 漫步, 徘徊, 迷路, 离题, 蜿蜒；vt. 在...漫游","definition":"v. go via an indirect route or at no set pace","pos":"vi. 不及物动词","level":"本龄重点","frequency":1},{"word":"whistle","phonetic":"'hwisl","translation":"n. 口哨, 汽笛, 啸啸声, 口哨声；vi. 吹口哨, 鸣汽笛, 发嘘嘘声","definition":"n. the sound made by something moving rapidly or by steam coming out of a small aperture","pos":"n. 名词","level":"拓展挑战","frequency":1},{"word":"accustomed","phonetic":"ә'kʌstәmd","translation":"a. 惯常的, 习惯了的","definition":"a. (often followed by `to') in the habit of or adapted to","pos":"adj. 形容词","level":"拓展挑战","frequency":3},{"word":"earlier","phonetic":"","translation":"a. 早的；初期的","definition":"s. (comparative and superlative of `early') more early than; most early","pos":"adj. 形容词","level":"基础巩固","frequency":1},{"word":"gay","phonetic":"gei","translation":"a. 欢快的, 艳丽的, 快乐的, 放荡的","definition":"s. full of or showing high-spirited merriment","pos":"adj. 形容词","level":"基础巩固","frequency":1},{"word":"angrily","phonetic":"'æŋgrili","translation":"adv. 愤怒地","definition":"r. with anger","pos":"adv. 副词","level":"拓展挑战","frequency":2},{"word":"cannot","phonetic":"'kænɒt","translation":"aux. 无法, 不能","definition":"Am, is, or are, not able; -- written either as one word or","pos":"重点词","level":"本龄重点","frequency":2},{"word":"occasionally","phonetic":"ә'keiʒәnli","translation":"adv. 有时候, 偶而","definition":"r. now and then or here and there","pos":"adv. 副词","level":"基础巩固","frequency":2},{"word":"choir","phonetic":"'kwaiә","translation":"n. 唱诗班, 唱诗班的席位；v. 合唱","definition":"n. a chorus that sings as part of a religious ceremony","pos":"n. 名词","level":"本龄重点","frequency":2},{"word":"gaze","phonetic":"geiz","translation":"n. 注视, 凝视；vi. 注视, 凝视","definition":"n. a long fixed look","pos":"n. 名词","level":"本龄重点","frequency":2},{"word":"pray","phonetic":"prei","translation":"v. 祈祷, 恳求, 请","definition":"v. address a deity, a prophet, a saint or an object of worship; say a prayer","pos":"v. 动词","level":"基础巩固","frequency":2},{"word":"sheer","phonetic":"ʃiә","translation":"a. 绝对的, 全然的, 纯粹的, 透明的, 峻峭的；vi. 偏转, 偏航","definition":"v. cause to sheer","pos":"adj. 形容词","level":"本龄重点","frequency":2},{"word":"straw","phonetic":"strɒ:","translation":"n. 稻草, 麦管, 吸管, 一文不值的东西, 草帽；a. 稻草的, 稻草色的, 琐碎的, 无价值的","definition":"n. plant fiber used e.g. for making baskets and hats or as fodder","pos":"n. 名词","level":"本龄重点","frequency":2},{"word":"terror","phonetic":"'terә","translation":"n. 恐怖, 可怕的人","definition":"n. a person who inspires fear or dread","pos":"n. 名词","level":"基础巩固","frequency":2},{"word":"comfortably","phonetic":"'kʌmfәtәbli","translation":"adv. 安乐地, 舒服地, 宽裕地","definition":"r. in mental comfort; without stress","pos":"adv. 副词","level":"拓展挑战","frequency":1},{"word":"happily","phonetic":"'hæpili","translation":"adv. 幸福地, 快乐地, 幸好","definition":"r. in a joyous manner","pos":"adv. 副词","level":"本龄重点","frequency":1},{"word":"seal","phonetic":"si:l","translation":"n. 印章, 封条, 海豹, 海豹皮, 火漆, 封蜡, 玺, 保证, 批准, 象征, 标志；vt. 封闭, 盖印, 盖章","definition":"n. a device incised to make an impression; used to secure a closing or to authenticate documents","pos":"n. 名词","level":"本龄重点","frequency":1},{"word":"treasure","phonetic":"'treʒә","translation":"n. 宝物, 财富；vt. 珍爱, 重视, 秘藏","definition":"n. accumulated wealth in the form of money or jewels etc.","pos":"n. 名词","level":"本龄重点","frequency":1},{"word":"worse","phonetic":"wә:s","translation":"n. 更坏的事, 更恶劣的事, 败局；a. 更坏的, 更恶劣的","definition":"n. something inferior in quality or condition or effect","pos":"n. 名词","level":"拓展挑战","frequency":1},{"word":"bare","phonetic":"bєә","translation":"a. 赤裸的, 缺少的, 无遮蔽的, 坦率的；vt. 使赤裸, 露出","definition":"v. lay bare","pos":"adj. 形容词","level":"本龄重点","frequency":1},{"word":"cave","phonetic":"keiv","translation":"n. 洞, 穴；vi. 凹陷, 塌落","definition":"n. a geological formation consisting of an underground enclosure with access from the surface of the ground or from the sea","pos":"n. 名词","level":"本龄重点","frequency":1},{"word":"continually","phonetic":"kәn'tinjuәli","translation":"adv. 不断地, 频繁地","definition":"r. seemingly without interruption","pos":"adv. 副词","level":"本龄重点","frequency":3},{"word":"eating","phonetic":"'i:tiŋ","translation":"n. 吃, 食物；a. 侵蚀的, 腐蚀性的","definition":"n. the act of consuming food","pos":"n. 名词","level":"本龄重点","frequency":3},{"word":"fool","phonetic":"fu:l","translation":"n. 愚人, 受骗者, 奶油拌水果；vt. 愚弄, 欺骗, 浪费","definition":"n. a person who lacks good judgment","pos":"n. 名词","level":"本龄重点","frequency":1},{"word":"illustration","phonetic":".ilә'streiʃәn","translation":"n. 例证, 插图","definition":"n. artwork that helps make something clear or attractive","pos":"n. 名词","level":"本龄重点","frequency":3},{"word":"lap","phonetic":"læp","translation":"n. 膝盖, 舔, 一圈, 下摆, 衣兜, 山坳；vi. 重叠, 围住, 轻拍, 舔","definition":"n. the upper side of the thighs of a seated person","pos":"n. 名词","level":"本龄重点","frequency":1},{"word":"recovery","phonetic":"ri'kʌvәri","translation":"n. 恢复, 复原, 痊愈, 重获","definition":"n. return to an original state","pos":"n. 名词","level":"基础巩固","frequency":1},{"word":"waiting","phonetic":"'weitiŋ","translation":"n. 等候；a. 等候的, 服侍的","definition":"s. being and remaining ready and available for use","pos":"n. 名词","level":"拓展挑战","frequency":3},{"word":"pasture","phonetic":"'pæstʃә","translation":"n. 牧场, 草地, 牧草；vt. 放牧","definition":"n. a field covered with grass or herbage and suitable for grazing by livestock","pos":"n. 名词","level":"拓展挑战","frequency":2},{"word":"amazed","phonetic":"ә'meizd","translation":"a. 吃惊的, 惊奇的","definition":"s. filled with the emotional impact of overwhelming surprise or shock","pos":"adj. 形容词","level":"拓展挑战","frequency":1},{"word":"carefully","phonetic":"'kєәfuli","translation":"adv. 小心地, 谨慎地","definition":"r. taking care or paying attention","pos":"adv. 副词","level":"基础巩固","frequency":1},{"word":"closely","phonetic":"'klәusli","translation":"adv. 接近地","definition":"r. in a close relation or position in time or space","pos":"adv. 副词","level":"基础巩固","frequency":1},{"word":"departure","phonetic":"di'pɑ:tʃә","translation":"n. 离开, 出发, 违背, 偏离","definition":"n. the act of departing","pos":"n. 名词","level":"基础巩固","frequency":1},{"word":"expected","phonetic":"","translation":"a. 预期的；预料的","definition":"a. considered likely or probable to happen or arrive","pos":"adj. 形容词","level":"本龄重点","frequency":1},{"word":"firmly","phonetic":"'fә:mli","translation":"adv. 坚固, 坚定, 断然","definition":"r with resolute determination","pos":"adv. 副词","level":"基础巩固","frequency":1},{"word":"gently","phonetic":"'dʒentli","translation":"adv. 温和地, 温柔地, 轻轻地, 逐渐地","definition":"r. in a gradual manner","pos":"adv. 副词","level":"基础巩固","frequency":1},{"word":"gray","phonetic":"grei","translation":"n. 灰色, 暗淡；a. 灰色的, 灰白的, 面色苍白的, 年老的, 老练的, 阴沉的","definition":"n. a neutral achromatic color midway between white and black","pos":"n. 名词","level":"基础巩固","frequency":1},{"word":"lightly","phonetic":"'laitli","translation":"adv. 轻轻地, 少许, 不费力地","definition":"r. without good reason","pos":"adv. 副词","level":"本龄重点","frequency":1},{"word":"proudly","phonetic":"'praudli","translation":"adv. 傲慢地, 自大地, 得意洋洋地","definition":"r. with pride; in a proud manner","pos":"adv. 副词","level":"拓展挑战","frequency":1},{"word":"rose","phonetic":"rәuz","translation":"n. 玫瑰, 蔷薇, 玫瑰色；a. 玫瑰色的, 玫瑰花的","definition":"n. any of many shrubs of the genus Rosa that bear roses","pos":"n. 名词","level":"基础巩固","frequency":1},{"word":"significantly","phonetic":"","translation":"adv. 值得注目地；意味深长地","definition":"r. in a statistically significant way","pos":"adv. 副词","level":"基础巩固","frequency":1},{"word":"softly","phonetic":"'sɒftli","translation":"adv. 柔和地, 静静地, 温柔地","definition":"r. with low volume","pos":"adv. 副词","level":"本龄重点","frequency":1},{"word":"surprised","phonetic":"sә'praizd","translation":"a. 感到惊讶的","definition":"a. taken unawares or suddenly and feeling wonder or astonishment","pos":"adj. 形容词","level":"基础巩固","frequency":1},{"word":"thanks","phonetic":"","translation":"n. 感谢, 谢意, 谢忱；interj. 谢谢, 谢谢你","definition":"n. an acknowledgment of appreciation","pos":"n. 名词","level":"基础巩固","frequency":1},{"word":"beast","phonetic":"bi:st","translation":"n. 畜生, 动物, 野兽, 兽性","definition":"n. a cruelly rapacious person","pos":"n. 名词","level":"本龄重点","frequency":1},{"word":"binding","phonetic":"'baindiŋ","translation":"n. 装订","definition":"n. the capacity to attract and hold something","pos":"n. 名词","level":"本龄重点","frequency":1},{"word":"blessing","phonetic":"'blesiŋ","translation":"n. 祝福","definition":"n. the formal act of approving","pos":"n. 名词","level":"本龄重点","frequency":1},{"word":"breeze","phonetic":"bri:z","translation":"n. 微风, 煤屑, 轻而易举的事；vi. 吹微风, 逃走","definition":"n. a slight wind (usually refreshing)","pos":"n. 名词","level":"本龄重点","frequency":1},{"word":"caution","phonetic":"'kɒ:ʃәn","translation":"n. 小心, 慎重, 警示；vt. 警告","definition":"n. the trait of being cautious; being attentive to possible danger","pos":"n. 名词","level":"本龄重点","frequency":1},{"word":"cling","phonetic":"kliŋ","translation":"vi. 粘紧, 附着, 紧贴, 坚持","definition":"n. fruit (especially peach) whose flesh adheres strongly to the pit","pos":"vi. 不及物动词","level":"本龄重点","frequency":1},{"word":"collar","phonetic":"'kɒlә","translation":"n. 衣领, 颈圈；vt. 控制, 扭住衣领, 给...装上领子","definition":"n. a band that fits around the neck and is usually folded over","pos":"n. 名词","level":"本龄重点","frequency":1},{"word":"conceal","phonetic":"kәn'si:l","translation":"vt. 隐藏, 掩盖, 隐瞒","definition":"v. hold back; keep from being perceived by others","pos":"vt. 及物动词","level":"本龄重点","frequency":1},{"word":"confess","phonetic":"kәn'fes","translation":"v. 承认, 坦白, 忏悔, 供认","definition":"v. confess to a punishable or reprehensible deed, usually under pressure","pos":"v. 动词","level":"本龄重点","frequency":1},{"word":"conscience","phonetic":"'kɒnʃәns","translation":"n. 良心","definition":"n. motivation deriving logically from ethical or moral principles that govern a person's thoughts and actions","pos":"n. 名词","level":"本龄重点","frequency":1},{"word":"contrary","phonetic":"'kɒntrәri","translation":"a. 相反的, 矛盾的, 对立的；n. 相反, 对立面","definition":"n. exact opposition","pos":"adj. 形容词","level":"本龄重点","frequency":1},{"word":"cord","phonetic":"kɒ:d","translation":"n. 绳索, 束缚","definition":"n. a line made of twisted fibers or threads","pos":"n. 名词","level":"本龄重点","frequency":1},{"word":"corn","phonetic":"kɒ:n","translation":"n. 玉蜀黍, 谷类, 谷粒, 鸡眼；vt. 使成颗粒, 腌","definition":"n. tall annual cereal grass bearing kernels on large ears: widely cultivated in America in many varieties; the principal cereal in Mexico and Central and South ","pos":"n. 名词","level":"基础巩固","frequency":1},{"word":"costly","phonetic":"'kɒstli","translation":"a. 昂贵的, 奢华的, 费用大的","definition":"s. having a high price","pos":"adj. 形容词","level":"本龄重点","frequency":1},{"word":"curiosity","phonetic":".kjuәri'ɒsiti","translation":"n. 好奇心, 新奇的事物, 珍品","definition":"n. a state in which you want to learn more about something","pos":"n. 名词","level":"本龄重点","frequency":1},{"word":"dawn","phonetic":"dɒ:n","translation":"n. 破晓, 黎明；vi. 破晓","definition":"n. the first light of day","pos":"n. 名词","level":"本龄重点","frequency":1},{"word":"delightful","phonetic":"di'laitful","translation":"a. 令人愉快的, 可爱的","definition":"s. greatly pleasing or entertaining","pos":"adj. 形容词","level":"拓展挑战","frequency":1},{"word":"distant","phonetic":"'distәnt","translation":"a. 远的, 疏远的","definition":"a. separated in space or coming from or going to a distance","pos":"adj. 形容词","level":"基础巩固","frequency":1},{"word":"doubtful","phonetic":"'dautful","translation":"a. 可疑的, 疑心的, 不明确的","definition":"s. open to doubt or suspicion","pos":"adj. 形容词","level":"本龄重点","frequency":1},{"word":"dried","phonetic":"draid","translation":"a. 弄干了的","definition":"s. not still wet","pos":"adj. 形容词","level":"本龄重点","frequency":1},{"word":"endless","phonetic":"'endlis","translation":"a. 不停的, 无穷尽的, 无尽的；[机] 无端的, 环状的","definition":"s. tiresomely long; seemingly without end","pos":"adj. 形容词","level":"本龄重点","frequency":1},{"word":"endure","phonetic":"in'djuә","translation":"vt. 忍受, 忍耐, 容忍, 耐；vi. (正式)持久, 持续","definition":"v put up with something or somebody unpleasant","pos":"vt. 及物动词","level":"本龄重点","frequency":1},{"word":"farewell","phonetic":"'fєә'wel","translation":"n. 辞别, 再见, 再会；interj. 再会","definition":"n. an acknowledgment or expression of goodwill at parting","pos":"n. 名词","level":"拓展挑战","frequency":1},{"word":"feast","phonetic":"fi:st","translation":"n. 宴会, 酒席, 享受, 节日；vt. 款待, 享乐, 请客","definition":"n. something experienced with great delight","pos":"n. 名词","level":"拓展挑战","frequency":1},{"word":"fog","phonetic":"fɒg","translation":"n. 雾, 迷惑, (割后的)最生草, 苔藓；vi. 被雾笼罩, 变模糊","definition":"n. droplets of water vapor suspended in the air near the ground","pos":"n. 名词","level":"本龄重点","frequency":1},{"word":"fond","phonetic":"fɒnd","translation":"a. 喜欢的, 宠爱的, 温柔的","definition":"s. (followed by `of' or `to') having a strong preference or liking for","pos":"adj. 形容词","level":"本龄重点","frequency":1},{"word":"foolish","phonetic":"'fu:liʃ","translation":"a. 愚蠢的, 傻的","definition":"a. devoid of good sense or judgment","pos":"adj. 形容词","level":"本龄重点","frequency":1},{"word":"fortunately","phonetic":"'fɒitʃәnitli","translation":"adv. 幸运地, 幸亏","definition":"r. by good fortune","pos":"adv. 副词","level":"本龄重点","frequency":1},{"word":"gloomy","phonetic":"'glu:mi","translation":"a. 抑沉的, 忧闷的, 黑暗的, 悲观的","definition":"s. filled with melancholy and despondency","pos":"adj. 形容词","level":"拓展挑战","frequency":1},{"word":"grief","phonetic":"gri:f","translation":"n. 伤心, 忧愁, 悲痛, 不幸, 灾难","definition":"n. intense sorrow caused by loss of a loved one (especially by death)","pos":"n. 名词","level":"本龄重点","frequency":1},{"word":"hidden","phonetic":"'hidn","translation":"a. 隐藏的；hide的过去分词","definition":"s. designed to elude detection","pos":"adj. 形容词","level":"本龄重点","frequency":1},{"word":"horrible","phonetic":"'hɒrәbl","translation":"a. 可怕的, 遭透的, 极讨厌的","definition":"s provoking horror","pos":"adj. 形容词","level":"本龄重点","frequency":1},{"word":"hunger","phonetic":"'hʌŋgә","translation":"n. 饥饿, 渴望, 饥荒；vt. 使挨饿","definition":"n. a physiological need for food; the consequence of food deprivation","pos":"n. 名词","level":"本龄重点","frequency":1},{"word":"inquire","phonetic":"in'kwaiә","translation":"v. 询问, 问明, 查究","definition":"v inquire about","pos":"v. 动词","level":"拓展挑战","frequency":1},{"word":"keeper","phonetic":"'ki:pә","translation":"n. 监护人, 管理人, 看守人；[机] 保管人, 看守人, 保持片","definition":"n. someone in charge of other people","pos":"n. 名词","level":"本龄重点","frequency":1},{"word":"maid","phonetic":"meid","translation":"n. 少女, 未婚女子, 女仆","definition":"n. a female domestic","pos":"n. 名词","level":"本龄重点","frequency":1},{"word":"making","phonetic":"'meikiŋ","translation":"n. 制造, (手工)制造业, 制作, 形成, 发展, 要素, 内在因素, 赚头, 制造物","definition":"n. (usually plural) the components needed for making or doing something","pos":"n. 名词","level":"本龄重点","frequency":1},{"word":"meantime","phonetic":"'mi:ntaim","translation":"n. 间隔时间, 其时；adv. 其间","definition":"n the time between one event, process, or period and another","pos":"n. 名词","level":"本龄重点","frequency":1},{"word":"murmur","phonetic":"'mә:mә","translation":"n. 低语, 低声的怨言；vi. 低语, 低声而言","definition":"v. speak softly or indistinctly","pos":"n. 名词","level":"本龄重点","frequency":1},{"word":"reflection","phonetic":"ri'flekʃәn","translation":"n. 反映, 沉思, 映像, 想法, 责难","definition":"n. the phenomenon of a propagating wave (light or sound) being thrown back from a surface","pos":"n. 名词","level":"基础巩固","frequency":1},{"word":"refuge","phonetic":"'refju:dʒ","translation":"n. 避难所, 安全地带, 避难, 庇护；vi. 躲避","definition":"n. a shelter from danger or hardship","pos":"n. 名词","level":"本龄重点","frequency":1},{"word":"robust","phonetic":"rәu'bʌst","translation":"a. 健康的, 强健的, 要用力气的, 坚定的, 粗野的","definition":"a. sturdy and strong in form, constitution, or construction","pos":"adj. 形容词","level":"拓展挑战","frequency":1},{"word":"shrub","phonetic":"ʃrʌb","translation":"n. 矮树, 灌木, 果汁甜酒","definition":"n. a low woody perennial plant usually having several major stems","pos":"n. 名词","level":"拓展挑战","frequency":1},{"word":"tender","phonetic":"'tendә","translation":"a. 嫩的, 柔软的, 脆弱的, 温柔的, 亲切的, 未成熟的, 微妙的, 棘手的, 审慎的；vt. 使变嫩, 提供, 偿还","definition":"n. something that can be used as an official medium of payment","pos":"adj. 形容词","level":"本龄重点","frequency":1},{"word":"troubled","phonetic":"'trʌbld","translation":"a. 烦恼的, 混乱的, 不安的","definition":"a. characterized by or indicative of distress or affliction or danger or need","pos":"adj. 形容词","level":"本龄重点","frequency":1},{"word":"trunk","phonetic":"trʌŋk","translation":"n. 树干, 干线, 躯干, 主干, 象鼻, 箱子；vt. 把...放入旅行箱内","definition":"n. the main stem of a tree; usually covered with bark; the bole is usually the part that is commercially useful for lumber","pos":"n. 名词","level":"本龄重点","frequency":1},{"word":"velvet","phonetic":"'velvit","translation":"n. 天鹅绒；a. 天鹅绒的","definition":"n. a silky densely piled fabric with a plain back","pos":"n. 名词","level":"拓展挑战","frequency":1},{"word":"verse","phonetic":"vә:s","translation":"n. 诗, 韵文, 诗句；vt. 用诗表达","definition":"n. a piece of poetry","pos":"n. 名词","level":"本龄重点","frequency":1},{"word":"vine","phonetic":"vain","translation":"n. 藤本植物, 葡萄, 藤, 蔓；vi. 形成藤蔓","definition":"n. a plant with a weak stem that derives support from climbing, twining, or creeping along a surface","pos":"n. 名词","level":"拓展挑战","frequency":1},{"word":"billy","phonetic":"'bili","translation":"n. 警棍, 伙伴","definition":"n. male goat","pos":"n. 名词","level":"本龄重点","frequency":2},{"word":"elizabeth","phonetic":"i'lizәbәθ","translation":"n. 伊丽莎白（女子名）","definition":"n. daughter of George VI who became the Queen of England and Northern Ireland in 1952 on the death of her father (1926-)","pos":"n. 名词","level":"基础巩固","frequency":2},{"word":"iii","phonetic":"","translation":"num. 罗马数字3","definition":"n the cardinal number that is the sum of one and one and one","pos":"重点词","level":"基础巩固","frequency":2},{"word":"sitting","phonetic":"'sitiŋ","translation":"n. 入席, 就坐, 开庭, 孵卵；a. 坐着的, 就座的, 在职的, 在孵卵中的, 易被击中的","definition":"n. (photography) the act of assuming a certain position (as for a photograph or portrait)","pos":"n. 名词","level":"拓展挑战","frequency":2},{"word":"boulder","phonetic":"'bәuldә","translation":"n. 大圆石；[机] 圆石, 漂石","definition":"n. a large smooth mass of rock detached from its place of origin","pos":"n. 名词","level":"拓展挑战","frequency":1},{"word":"dearest","phonetic":"","translation":"n. 最亲爱的人","definition":"n a beloved person; used as terms of endearment","pos":"n. 名词","level":"本龄重点","frequency":1},{"word":"exclaim","phonetic":"iks'kleim","translation":"v. 大叫, 呼喊, 大声叫","definition":"v. utter aloud; often with surprise, horror, or joy","pos":"v. 动词","level":"拓展挑战","frequency":1},{"word":"pant","phonetic":"pænt","translation":"n. 喘息, 悸动；vi. 喘息, 渴望","definition":"n. the noise made by a short puff of steam (as from an engine)","pos":"n. 名词","level":"基础巩固","frequency":1},{"word":"plainly","phonetic":"'pleinli","translation":"adv. 清楚地, 明白地, 简单地, 朴素地, 直率地, 坦白地","definition":"r. in a simple manner; without extravagance or embellishment","pos":"adv. 副词","level":"拓展挑战","frequency":1},{"word":"rocky","phonetic":"'rɒki","translation":"a. 岩石的, 多石的, 像岩石的, 无情的, 摇动的, 摇晃的","definition":"s. abounding in rocks or stones","pos":"adj. 形容词","level":"拓展挑战","frequency":1},{"word":"rugged","phonetic":"'rʌgid","translation":"a. 高低不平的, 崎岖的, 粗糙的","definition":"a. sturdy and strong in constitution or construction; enduring","pos":"adj. 形容词","level":"拓展挑战","frequency":1},{"word":"chosen","phonetic":"'tʃouzn","translation":"choose的过去分词","definition":"n. one who is the object of choice; who is given preference","pos":"重点词","level":"拓展挑战","frequency":1},{"word":"continued","phonetic":"kәn'tinju:d","translation":"a. 继续的, 延续的","definition":"a. without stop or interruption","pos":"adj. 形容词","level":"本龄重点","frequency":1},{"word":"enduring","phonetic":"in'djuәriŋ","translation":"a. 持久的, 忍耐的","definition":"s. patiently bearing continual wrongs or trouble","pos":"adj. 形容词","level":"拓展挑战","frequency":1},{"word":"exceptionally","phonetic":"","translation":"adv. 特殊地；异常地；例外地","definition":"r. to an exceptional degree","pos":"adv. 副词","level":"拓展挑战","frequency":1},{"word":"frankly","phonetic":"'fræŋkli","translation":"adv. 坦白地","definition":"r (used as intensives reflecting the speaker's attitude) it is sincerely the case that","pos":"adv. 副词","level":"本龄重点","frequency":1},{"word":"growing","phonetic":"'grәuiŋ","translation":"a. 成长的","definition":"n. (electronics) the production of (semiconductor) crystals by slow crystallization from the molten state","pos":"adj. 形容词","level":"基础巩固","frequency":1},{"word":"helen","phonetic":"'helәn","translation":"n. 海伦（女子名, 火把、光亮的之义）","definition":"n. (Greek mythology) the beautiful daughter of Zeus and Leda who was abducted by Paris; the Greek army sailed to Troy to get her back which resulted in the Troj","pos":"n. 名词","level":"基础巩固","frequency":1},{"word":"humor","phonetic":"'hju:mә","translation":"n. 幽默, 诙谐, 心情；vt. 迎合, 牵就, 顺应","definition":"n. the trait of appreciating (and being able to express) the humorous","pos":"n. 名词","level":"本龄重点","frequency":1},{"word":"known","phonetic":"nәun","translation":"a. 已知的, 有名的；know的过去分词","definition":"a. apprehended with certainty","pos":"adj. 形容词","level":"本龄重点","frequency":1},{"word":"loved","phonetic":"lʌvd","translation":"v. 热爱（love的过去分词）","definition":"a. held dear","pos":"v. 动词","level":"拓展挑战","frequency":1},{"word":"meditation","phonetic":".medi'teiʃәn","translation":"n. 沉思, 冥想","definition":"n. continuous and profound contemplation or musing on a subject or series of subjects of a deep or abstruse nature","pos":"n. 名词","level":"拓展挑战","frequency":1},{"word":"planned","phonetic":"plænd","translation":"a. 计划了的, 预定的, 根据计划的, 有组织的","definition":"a. designed or carried out according to a plan","pos":"adj. 形容词","level":"本龄重点","frequency":1},{"word":"protected","phonetic":"","translation":"a. 受保护的","definition":"a. kept safe or defended from danger or injury or loss","pos":"adj. 形容词","level":"拓展挑战","frequency":1},{"word":"raised","phonetic":"reizd","translation":"a. 凸起的, 浮雕的, 发酵的","definition":"a. located or moved above the surround or above the normal position","pos":"adj. 形容词","level":"拓展挑战","frequency":1},{"word":"shared","phonetic":"ʃεәd","translation":"a. 共享的","definition":"a. have in common; held or experienced in common","pos":"adj. 形容词","level":"本龄重点","frequency":1},{"word":"smiling","phonetic":"'smailiŋ","translation":"a. 微笑的, 欢快的","definition":"n a facial expression characterized by turning up the corners of the mouth; usually shows pleasure or amusement","pos":"adj. 形容词","level":"拓展挑战","frequency":1},{"word":"vigorously","phonetic":"","translation":"adv. 朝气蓬勃, 精力充沛, 壮健, 茁壮, 健壮, 强有力","definition":"r. with vigor; in a vigorous manner","pos":"adv. 副词","level":"拓展挑战","frequency":1},{"word":"visiting","phonetic":"'vizitiŋ","translation":"n. 参观, 拜访, 访问","definition":"n. the activity of making visits","pos":"n. 名词","level":"本龄重点","frequency":1}]}