{
  "version": "6",
  "dialect": "sqlite",
  "id": "542171ae-f5e8-435c-90e6-81397e070feb",
  "prevId": "00000000-0000-0000-0000-000000000000",
  "tables": {
    "reader_friendships": {
      "name": "reader_friendships",
      "columns": {
        "owner_id": {
          "name": "owner_id",
          "type": "text",
          "primaryKey": false,
          "notNull": true,
          "autoincrement": false
        },
        "friend_id": {
          "name": "friend_id",
          "type": "text",
          "primaryKey": false,
          "notNull": true,
          "autoincrement": false
        },
        "created_at": {
          "name": "created_at",
          "type": "text",
          "primaryKey": false,
          "notNull": true,
          "autoincrement": false,
          "default": "CURRENT_TIMESTAMP"
        }
      },
      "indexes": {
        "reader_friendships_owner_idx": {
          "name": "reader_friendships_owner_idx",
          "columns": [
            "owner_id",
            "created_at"
          ],
          "isUnique": false
        }
      },
      "foreignKeys": {
        "reader_friendships_owner_id_reader_profiles_id_fk": {
          "name": "reader_friendships_owner_id_reader_profiles_id_fk",
          "tableFrom": "reader_friendships",
          "tableTo": "reader_profiles",
          "columnsFrom": [
            "owner_id"
          ],
          "columnsTo": [
            "id"
          ],
          "onDelete": "cascade",
          "onUpdate": "no action"
        },
        "reader_friendships_friend_id_reader_profiles_id_fk": {
          "name": "reader_friendships_friend_id_reader_profiles_id_fk",
          "tableFrom": "reader_friendships",
          "tableTo": "reader_profiles",
          "columnsFrom": [
            "friend_id"
          ],
          "columnsTo": [
            "id"
          ],
          "onDelete": "cascade",
          "onUpdate": "no action"
        }
      },
      "compositePrimaryKeys": {
        "reader_friendships_owner_id_friend_id_pk": {
          "columns": [
            "owner_id",
            "friend_id"
          ],
          "name": "reader_friendships_owner_id_friend_id_pk"
        }
      },
      "uniqueConstraints": {},
      "checkConstraints": {}
    },
    "reader_profiles": {
      "name": "reader_profiles",
      "columns": {
        "id": {
          "name": "id",
          "type": "text",
          "primaryKey": true,
          "notNull": true,
          "autoincrement": false
        },
        "friend_code": {
          "name": "friend_code",
          "type": "text",
          "primaryKey": false,
          "notNull": true,
          "autoincrement": false
        },
        "secret_hash": {
          "name": "secret_hash",
          "type": "text",
          "primaryKey": false,
          "notNull": true,
          "autoincrement": false
        },
        "nickname": {
          "name": "nickname",
          "type": "text",
          "primaryKey": false,
          "notNull": true,
          "autoincrement": false
        },
        "completed_count": {
          "name": "completed_count",
          "type": "integer",
          "primaryKey": false,
          "notNull": true,
          "autoincrement": false,
          "default": 0
        },
        "started_count": {
          "name": "started_count",
          "type": "integer",
          "primaryKey": false,
          "notNull": true,
          "autoincrement": false,
          "default": 0
        },
        "total_progress": {
          "name": "total_progress",
          "type": "integer",
          "primaryKey": false,
          "notNull": true,
          "autoincrement": false,
          "default": 0
        },
        "progress_json": {
          "name": "progress_json",
          "type": "text",
          "primaryKey": false,
          "notNull": true,
          "autoincrement": false,
          "default": "'{}'"
        },
        "created_at": {
          "name": "created_at",
          "type": "text",
          "primaryKey": false,
          "notNull": true,
          "autoincrement": false,
          "default": "CURRENT_TIMESTAMP"
        },
        "updated_at": {
          "name": "updated_at",
          "type": "text",
          "primaryKey": false,
          "notNull": true,
          "autoincrement": false,
          "default": "CURRENT_TIMESTAMP"
        }
      },
      "indexes": {
        "reader_profiles_friend_code_idx": {
          "name": "reader_profiles_friend_code_idx",
          "columns": [
            "friend_code"
          ],
          "isUnique": true
        }
      },
      "foreignKeys": {},
      "compositePrimaryKeys": {},
      "uniqueConstraints": {},
      "checkConstraints": {}
    }
  },
  "views": {},
  "enums": {},
  "_meta": {
    "schemas": {},
    "tables": {},
    "columns": {}
  },
  "internal": {
    "indexes": {}
  }
}